Workbook

Sheet Leeme
A1: APAR-CAR - Backlog del producto v3.5
A2: Proyecto de grado - Tecnólogo en Análisis y Desarrollo de Software - Ficha 3229209 - SENA | Instructor: Deimer Miranda Montoya | Equipo: Ismael Mira Correa (frontend) | Valeria Usuga Penagos (backend) | Mariana Uribe Muñoz (analista y líder)
A3: Actualizado el 11 de septiembre de 2026. Entregable 3 del proyecto: documento de Backlog, Historias de Usuario y Casos de Uso. La v3.5 incorpora a HU-43 el criterio de aceptación sobre el acuse al dispositivo lector, detectado durante el modelado de la plantilla P04.
A5: QUE HAY EN ESTE LIBRO
A6: Resumen | B6: Métricas del backlog calculadas con fórmulas: total de puntos, reparto MoSCoW y porcentaje de esfuerzo en Must. Es lo que se mira primero para saber si el alcance de la primera versión es realista.
A7: Actores | B7: Quién usa el sistema, que necesita lograr y por qué le importa. Cada actor esta cruzado con su stakeholder (STK) del documento de Stakeholders.
A8: Épicas | B8: 8 épicas agrupadas por CAPACIDAD del sistema, no por pantalla. Los conteos y los puntos se calculan solos desde la hoja Historias de Usuario.
A9: Requisitos Funcionales | B9: 22 requisitos (RF-xx) con su origen y las historias que los implementan. Hoja nueva en la v3.2: el catálogo vivía únicamente en el Anexo A de la plantilla P01.
A10: Historias de Usuario | B10: 47 historias con criterios de aceptación en Dado/Cuando/Entonces y un escenario de error propio por historia. Es la hoja principal del libro.
A11: Reglas de Negocio | B11: 17 reglas (RN-xx) que aplican siempre, independientes de la pantalla. Se separan de las historias para no repetirlas en cada criterio de aceptación.
A12: Requisitos No Funcionales | B12: 11 requisitos (RNF-xx) con criterio de verificación y su riesgo asociado del documento Análisis de Seguridad. Un RNF que no se puede verificar no es un requisito.
A13: INVEST | B13: Checklist INVEST por historia, con observación donde hay algo que revisar.
A14: Trazabilidad | B14: Cadena Necesidad -> Stakeholder -> Épica -> Historia -> Regla/RNF -> Caso de prueba. Es el esqueleto de la matriz de trazabilidad de la fase de pruebas.
A15: Decisiones (ADR) | B15: 10 decisiones de arquitectura registradas, con alternativas evaluadas y consecuencias. Todas aceptadas: ADR-008 (stack tecnologico) se cerro el 11/09/2026 y ADR-010 (estilo arquitectonico) se creo en la v3.4.
A16: Fuera de alcance | B16: Lo que se decidió NO hacer y por qué. Documentar esto vale tanto como documentar lo que si se hace.
A17: Control de cambios | B17: Que cambio de la v2 a la v3, con su justificación. Incluye las correcciones pendientes en los demás entregables del proyecto.
... A20: Supuestos | B20: SUP-03: condiciones que se dan por ciertas y de las que dependen partes del alcance. Si un supuesto se cae, se cae lo que sostiene.
A22: COMO SE USA
A23: Celdas amarillas | B23: Son las que el equipo debe diligenciar o confirmar. Todo lo demás ya viene propuesto.
A24: Columna Estado | B24: Lista desplegable: Por hacer / En progreso / En revisión / Hecho. Es lo que se refleja en el tablero del equipo.
A25: Columnas MoSCoW y Puntos | B25: Listas desplegables. Si se cambia un valor, el Resumen y las Épicas se recalculan solos.
A26: Historia de referencia | B26: HU-04 (Cerrar mi sesión) anclada en 2 puntos. Todas las demás se estimaron comparándose con ella.
A27: Puntos, no horas | B27: La estimación es relativa. Un 8 es cuatro veces más grande que un 2, pero no equivale a un número fijo de horas.
A29: QUE CAMBIO FRENTE A LA v2 (detalle completo en la hoja Control de cambios)
A30: Nombre del proyecto | B30: El libro decía UrbanSpot. El proyecto se llama APAR-CAR y la ficha correcta es 3229209.
A31: Rol de operario | B31: Entra a la primera versión. El Acta de Constitución lo promete en el objetivo general y en el Entregable 5, y el documento de Stakeholders lo clasifica como STK-02 usuario clave. Antes estaba fuera de alcance: era una contradicción entre entregables.
A32: Visitante ocasional | B32: Deja de ser un actor pasivo. Ahora puede consultar su tiquete con un código entregado a la entrada, nunca con la placa (STK-04).
A33: Reglas de cobro | B33: RN-14 quedo definida: cobro proporcional por bloques de 24 horas, cobrando por bloque el menor entre el proporcional y la tarifa día, con cobro mínimo de una hora.
A34: Derecho de supresión | B34: HU-37 pasa de eliminar a inhabilitar y luego anonimizar, amparada en el deber contractual que reconoce la propia norma. Los registros de dinero sobreviven sin titular identificable.
A35: Historias divisibles | B35: HU-12 se dividió en HU-12a y HU-12b. HU-21 se mantiene unida con justificación escrita.
A36: Aviso de vencimiento | B36: La antigua HU-31 se retiro del alcance: exige un proceso programado y un servicio de correo que no aportan al nucleo de la v1.
A37: Decisiones cerradas | B37: Los supuestos SUP-01 y SUP-02 desaparecen. ADR-003 y ADR-004 pasan a Aceptada y se agregan ADR-005, ADR-006 y ADR-007.
A38: Trazabilidad ampliada | B38: Cada historia y cada necesidad quedan cruzadas con el stakeholder que la origina, y cada RNF con el riesgo del Análisis de Seguridad que mitiga.
A40: DECISIONES CERRADAS EL 14 DE AGOSTO DE 2026
A41: Modelo de espacios | B41: Celdas identificadas con código propio (A-01, A-02), no un contador. Confirmado por el Acta de Constitución. Ver ADR-003.
A42: Ciclo de facturación | B42: Rodante: 30 días calendario desde la fecha del pago. Evita el prorrateo. Ver ADR-004 y RN-11.
A43: Código de vinculación | B43: Vence a los 7 días. Ver RN-05.
A44: Estado Por vencer | B44: Se activa 3 días antes del vencimiento. Ver RN-12.
A45: Roles del sistema | B45: Tres roles con credenciales: administrador, operario y cliente afiliado. A ellos se suman Persona nueva y Cliente ocasional como actores sin rol. Ver ADR-005.
A47: PENDIENTE DE DILIGENCIAR POR EL EQUIPO
A48: Stack tecnológico | B48: El Acta lista MySQL, XAMPP, Visual Studio Code, GitHub y Figma como recursos, pero no hay un ADR que registre la decisión del lenguaje de servidor ni del framework. Falta ADR-008.
A49: Casos de prueba | B49: La ultima columna de la hoja Trazabilidad se completa en la fase de Pruebas y ajustes (01/12/2026 - 22/12/2026 según el cronograma del Acta).
A50: Parqueadero de referencia | B50: El Acta identifica como riesgo la poca disponibilidad de un parqueadero real para validar. Registrar aquí cual se consiguió y en que fecha se hizo la entrevista.

Sheet Resumen
A1: Resumen del backlog
A2: APAR-CAR v3.5 - Proyecto de grado - Tecnólogo en Análisis y Desarrollo de Software - Ficha 3229209. Actualizado el 11 de septiembre de 2026.
A3: Todo en esta hoja se calcula con fórmulas desde las demás hojas. No escriba valores a mano aquí.
A4: Indicador | B4: Valor | C4: Nota
A5: Total de historias de usuario | B5: =COUNTIF('Historias de Usuario'!$A$5:$A$200,"HU-*") -> 47 | C5: Mínimo exigido por la guía: 8
A6: Roles del sistema (con credenciales) | B6: 3 | C6: Administrador, Operario y Cliente afiliado. Mínimo exigido por la guía: 2
A7: Actores del sistema | B7: 5 | C7: Los 3 roles más Persona nueva y Cliente ocasional. Son los que aparecen en BPMN, secuencia y actividades
A8: Total de puntos del proyecto | B8: =SUM('Historias de Usuario'!$K$5:$K$200) -> 187 | C8: Estimación relativa, no horas
A9: Puntos en Must | B9: =SUMIF('Historias de Usuario'!$J$5:$J$200,"Must",'Historias de Usuario'!$K$5:$K$200) -> 111 | C9: Producto mínimo viable
A10: Puntos en Should | B10: =SUMIF('Historias de Usuario'!$J$5:$J$200,"Should",'Historias de Usuario'!$K$5:$K$200) -> 55 | C10: Importante, no bloqueante
A11: Puntos en Could | B11: =SUMIF('Historias de Usuario'!$J$5:$J$200,"Could",'Historias de Usuario'!$K$5:$K$200) -> 21 | C11: Si sobra capacidad
A12: % de esfuerzo en Must | B12: =IFERROR(B9/B8,0) -> 0.59358289 | C12: Referencia sana: entre 50% y 65%. Por encima de 70% el alcance del MVP está inflado
A13: Historias Must | B13: =COUNTIF('Historias de Usuario'!$J$5:$J$200,"Must") -> 27
A14: Historias Should | B14: =COUNTIF('Historias de Usuario'!$J$5:$J$200,"Should") -> 15
A15: Historias Could | B15: =COUNTIF('Historias de Usuario'!$J$5:$J$200,"Could") -> 5
A16: Historia de referencia | B16: HU-04 | C16: Cerrar mi sesión, anclada en 2 puntos. Todas las demás se estimaron contra ella
A17: Requisitos funcionales | B17: =COUNTIF('Requisitos Funcionales'!$A$5:$A$100,"RF-*") -> 22 | C17: Catálogo incorporado al backlog en la v3.2
A18: Reglas de negocio definidas | B18: =COUNTIF('Reglas de Negocio'!$A$5:$A$100,"RN-*") -> 17
A19: Requisitos no funcionales | B19: =COUNTIF('Requisitos No Funcionales'!$A$5:$A$100,"RNF-*") -> 11
A20: Decisiones de arquitectura | B20: =COUNTIF('Decisiones (ADR)'!$A$5:$A$100,"ADR-*") -> 10 | C20: 10 decisiones, todas aceptadas. ADR-008 (stack tecnologico) se cerro el 11/09/2026 y ADR-010 (estilo arquitectonico) se registro en la v3.4.
A21: Necesidades trazadas | B21: =COUNTIF(Trazabilidad!$A$5:$A$100,"NEC-*") -> 12 | C21: Cada una cruzada con su stakeholder de origen
A22: Elementos fuera de alcance | B22: =COUNTIF('Fuera de alcance'!$B$5:$B$100,"Won?t*") -> 12 | C22: Documentar el Won't es parte de la evidencia. Cuenta las filas marcadas como Won't en la hoja Fuera de alcance.
A23: Historias por hacer | B23: =COUNTIF('Historias de Usuario'!$L$5:$L$200,"Por hacer") -> 47 | C23: Se actualiza a medida que avanza el desarrollo
A24: Historias terminadas | B24: =COUNTIF('Historias de Usuario'!$L$5:$L$200,"Hecho") -> 0
A25: Avance del proyecto (%) | B25: =IFERROR(SUMIF('Historias de Usuario'!$L$5:$L$200,"Hecho",'Historias de Usuario'!$K$5:$K$200)/B8,0) -> 0 | C25: Puntos terminados sobre puntos totales
A26: Historias técnicas | B26: =COUNTIF('Historias Tecnicas'!$A$5:$A$100,"HT-*") -> 8 | C26: Trabajo de soporte justificado por una decisión de arquitectura
A27: Casos de uso especificados | B27: =COUNTIF('Casos de Uso'!$A$5:$A$100,"CU-*") -> 6 | C27: Solo los flujos con bifurcaciones que la historia no alcanza a mostrar
A28: Supuestos abiertos | B28: =COUNTIF(Supuestos!$A$5:$A$100,"SUP-*") -> 1 | C28: Condiciones de las que depende parte del alcance

Sheet Actores
A1: Actores y necesidades
A2: Para quien se escribe el software. El libro distingue tres categorías: los 3 ROLES del sistema, que tienen credenciales y permisos; los 5 ACTORES, que son los roles más Persona nueva y Cliente ocasional, y son quienes inician una interacción en los diagramas; y los 6 INTERESADOS del proyecto, que agregan al equipo de desarrollo y al instructor, quienes no operan el sistema.
A4: Actor / Rol | B4: Tipo | C4: Descripción | D4: Que necesita lograr | E4: Por qué le importa | F4: Épicas relacionadas | G4: Stakeholder
A5: Persona nueva | B5: Actor sin rol (no autenticado) | C5: Usuario no autenticado | D5: Crear una cuenta e ingresar al sistema por primera vez, indicando si administra un parqueadero o si es cliente de uno. | E5: Es su único camino de entrada. Si el registro es confuso o le pide datos que no tiene a la mano, abandona. | F5: EP-01 | G5: -
A6: Administrador | B6: Rol del sistema (con credenciales) | C6: Propietario del parqueadero | D6: Configurar su parqueadero, registrar sus operarios, afiliar clientes, cobrar y ver como va el negocio. Solo sobre SU parqueadero. | E6: Es su fuente de ingresos. Un error de cálculo o un cliente en mora que se le pasa es plata que pierde ese mismo día. | F6: EP-01 a EP-08 | G6: STK-01
A7: Operario | B7: Rol del sistema (con credenciales) | C7: Vigilante o portero de turno, creado por el administrador | D7: Registrar entradas y salidas con rapidez durante su turno y ver la ocupación, sin acceso a tarifas, cartera ni reportes. | E7: Es quién está realmente en la caseta. Si el registro le toma más pasos que el cuaderno, no lo usa y el sistema fracasa. | F7: EP-01, EP-04 | G7: STK-02
A8: Cliente afiliado | B8: Rol del sistema (con credenciales) | C8: Usuario del parqueadero, vinculado a uno o más parqueaderos | D8: Consultar el historial de su vehículo, saber si está al día y revisar sus pagos registrados. | E8: Paga una mensualidad y hoy no tiene forma de verificar nada. Quedar en mora sin saberlo le puede costar el cupo. | F8: EP-01, EP-03, EP-06, EP-08 | G8: STK-03
A9: Cliente ocasional | B9: Actor sin rol (sin credenciales) | C9: Visitante de paso, sin cuenta ni credenciales. No confundir con el cliente afiliado de modalidad por horas, que si tiene cuenta. | D9: Entrar, parquear y salir pagando por el tiempo usado, y poder consultar su tiquete abierto con el código que le dieron a la entrada. | E9: Es la mayor parte de los movimientos de un parqueadero pequeño. El sistema debe atenderlo sin obligarlo a registrarse. | F9: EP-04 | G9: STK-04
A10: Equipo de desarrollo | B10: Interesado del proyecto, no actor del sistema | C10: Actor del proyecto, no del sistema | D10: Contar con requisitos estables y un alcance delimitado para construir, documentar y sustentar la plataforma. | E10: Un backlog abierto obliga a rehacer trabajo ya hecho y pone en riesgo el cronograma del Acta de Constitución. | F10: - | G10: STK-05
A11: Instructor del programa | B11: Interesado del proyecto, no actor del sistema | C11: Evaluador y asesor, no usuario del sistema | D11: Verificar que el proyecto aplique correctamente los conceptos de ingenieria de software. | E11: Aprueba o rechaza los entregables academicos. Le importa sobre todo la coherencia entre acta, stakeholders y requerimientos. | F11: - | G11: STK-06

Sheet Requisitos Funcionales
A1: Requisitos funcionales
A2: Que debe hacer el sistema, con la estructura actor + acción + objeto + condición. Cada requisito se deriva de un objetivo específico del Acta, del documento de Stakeholders o del Análisis de Seguridad, y se implementa a traves de las historias de usuario que lo desarrollan. Catálogo incorporado al backlog en la v3.2: antes vivía únicamente en el Anexo A de la plantilla P01.
A4: ID | B4: Nombre del requisito | C4: Descripción | D4: Origen | E4: Épica | F4: Historias que lo implementan
A5: RF-01 | B5: Registro de cuentas de administrador y cliente | C5: Permitir que una persona nueva cree su cuenta indicando si administra un parqueadero o si es cliente de uno. El registro del administrador crea también su parqueadero. | D5: Acta, Objetivo Específico 2 | E5: EP-01 | F5: HU-01, HU-02
A6: RF-02 | B6: Autenticación y direccionamiento por rol | C6: Validar credenciales, abrir sesión, fijar el parqueadero desde la sesión y dirigir a cada usuario al panel que le corresponde según su rol. | D6: Acta, Objetivo Específico 2 | E6: EP-01 | F6: HU-03, HU-04, HU-46
A7: RF-03 | B7: Gestión del perfil y recuperación de contraseña | C7: Permitir a cada usuario actualizar sus datos, cambiar su contraseña y recuperar el acceso de forma autonoma. | D7: Acta, Objetivo Específico 2 | E7: EP-01 | F7: HU-05, HU-06
A8: RF-04 | B8: Administración de cuentas de operario | C8: Permitir al administrador crear, habilitar y desactivar cuentas de operario limitadas a su parqueadero y con permisos restringidos. | D8: Acta, Objetivo General y Específico 2 | E8: EP-01 | F8: HU-38, HU-39
A9: RF-05 | B9: Gestión del inventario de celdas | C9: Registrar las celdas del parqueadero con código único y tipo de vehículo permitido. | D9: Acta, Objetivo Específico 4 | E9: EP-02 | F9: HU-07, HU-08
A10: RF-06 | B10: Visualización de la ocupación en tiempo real | C10: Mostrar el estado actual de cada celda y la lista de vehículos presentes en el parqueadero. | D10: Acta, Objetivo Específico 4 | E10: EP-02, EP-04 | F10: HU-23, HU-33
A11: RF-07 | B11: Gestión y versionado de tarifas | C11: Definir los valores por hora, por día y por mensualidad, versionarlos con fecha de vigencia y consultar su histórico. | D11: Acta, Objetivo Específico 5 | E11: EP-02 | F11: HU-09, HU-11
A12: RF-08 | B12: Administración de los datos del parqueadero | C12: Permitir corregir o actualizar el nombre, la dirección y la ubicación del parqueadero. | D12: Acta, Objetivo Específico 1 | E12: EP-02 | F12: HU-10
A13: RF-09 | B13: Afiliación de clientes y vehículos | C13: Registrar clientes con sus vehículos, consultarlos, asociarles vehículos adicionales, cerrar vínculos por cambio de dueño y desactivar afiliaciones. | D13: Acta, Objetivo Específico 1 | E13: EP-03 | F13: HU-12a, HU-14, HU-15, HU-16, HU-17, HU-18
A14: RF-10 | B14: Vinculación del cliente mediante código | C14: Emitir, entregar y validar el código que permite al cliente asociar su cuenta a su vehículo y a un parqueadero. | D14: Acta, Objetivo Específico 1 + ADR-002 | E14: EP-03 | F14: HU-12b, HU-13
A15: RF-11 | B15: Registro de entrada de vehículos | C15: Registrar el ingreso de vehículos afiliados y ocasionales asignando una celda libre compatible y congelando la tarifa vigente. | D15: Acta, Objetivo Específico 3 | E15: EP-04 | F15: HU-19, HU-20
... A26: RF-22 | B26: Registro de movimientos mediante lector de código QR | C26: Permitir que un dispositivo lector envíe a la API el código QR leido en la entrada o en la salida, para que el operario confirme la placa y cierre el registro. El registro manual permanece disponible como vía alterna cuando el lector no esta operativo. | D26: Decisión del equipo 28/08/2026 + ADR-009 | E26: EP-04 | F26: HU-43, HU-44, HU-45
A28: Los 20 primeros requisitos se tomaron integros del Anexo A de la plantilla P01. RF-21 y RF-22 son nuevos en la v3.2 y recogen la decisión de registrar los movimientos con lector de código QR (ADR-009).

Sheet Epicas
A1: Épicas
A2: Agrupadas por capacidad del sistema, no por pantalla. Las tres ultimas columnas se calculan solas desde la hoja Historias de Usuario.
A4: ID | B4: Titulo de la épica | C4: Descripción | D4: Objetivo de negocio / valor | E4: N historias | F4: Puntos | G4: % del total
A5: EP-01 | B5: Identidad y acceso | C5: Creación de cuentas, autenticación con tres roles, creación de operarios, recuperación de contraseña y gestión del perfil propio. Es la única puerta de entrada al sistema. | D5: Que cada persona entre de forma segura y que el sistema sepa automáticamente que información mostrarle según su rol. | E5: =COUNTIF('Historias de Usuario'!$B$5:$B$200,$A5) -> 9 | F5: =SUMIF('Historias de Usuario'!$B$5:$B$200,$A5,'Historias de Usuario'!$K$5:$K$200) -> 30 | G5: =IFERROR(F5/SUM($F$5:$F$12),0) -> 0.16042781
A6: EP-02 | B6: Configuración del parqueadero | C6: Datos del parqueadero, inventario de celdas identificadas y tarifas versionadas. Es lo que el administrador deja listo una vez para que la operación diaria funcione sola. | D6: Que el administrador configure su negocio una sola vez y el sistema calcule todo lo demás sin intervención manual. | E6: =COUNTIF('Historias de Usuario'!$B$5:$B$200,$A6) -> 5 | F6: =SUMIF('Historias de Usuario'!$B$5:$B$200,$A6,'Historias de Usuario'!$K$5:$K$200) -> 21 | G6: =IFERROR(F6/SUM($F$5:$F$12),0) -> 0.11229947
A7: EP-03 | B7: Afiliación de clientes y vehículos | C7: Vínculo entre una persona, un vehículo y un parqueadero. Incluye el registro que hace el administrador, el código de vinculación y el cierre del vínculo por cambio de dueño. | D7: Que cada cliente quede correctamente asociado a su parqueadero y a su vehículo, sin duplicados y sin que nadie pueda reclamar información ajena. | E7: =COUNTIF('Historias de Usuario'!$B$5:$B$200,$A7) -> 10 | F7: =SUMIF('Historias de Usuario'!$B$5:$B$200,$A7,'Historias de Usuario'!$K$5:$K$200) -> 36 | G7: =IFERROR(F7/SUM($F$5:$F$12),0) -> 0.19251337
A8: EP-04 | B8: Operación diaria de entradas y salidas | C8: El nucleo del sistema: registrar quien entra, quien sale, cuanto tiempo estuvo y cuanto debe pagar. Cubre al cliente afiliado y al ocasional, y es la épica que más usa el operario. | D8: Que el control de acceso y el cobro dejen de hacerse a mano, eliminando errores de cálculo y perdida de ingresos. | E8: =COUNTIF('Historias de Usuario'!$B$5:$B$200,$A8) -> 9 | F8: =SUMIF('Historias de Usuario'!$B$5:$B$200,$A8,'Historias de Usuario'!$K$5:$K$200) -> 42 | G8: =IFERROR(F8/SUM($F$5:$F$12),0) -> 0.22459893
A9: EP-05 | B9: Cartera y pagos de mensualidades | C9: Estado de cuenta de los clientes mensuales, registro de pagos, detección de mora y carta de cobro. | D9: Que el administrador sepa en todo momento quien le debe y cuanto, sin depender de cuadernos. | E9: =COUNTIF('Historias de Usuario'!$B$5:$B$200,$A9) -> 5 | F9: =SUMIF('Historias de Usuario'!$B$5:$B$200,$A9,'Historias de Usuario'!$K$5:$K$200) -> 23 | G9: =IFERROR(F9/SUM($F$5:$F$12),0) -> 0.12299465
A10: EP-06 | B10: Portal del cliente | C10: Vista propia del cliente sobre su vehículo: historial de movimientos, estado de su mensualidad y sus pagos registrados. | D10: Que el cliente consulte su propia información sin tener que preguntarle al administrador, generando transparencia. | E10: =COUNTIF('Historias de Usuario'!$B$5:$B$200,$A10) -> 3 | F10: =SUMIF('Historias de Usuario'!$B$5:$B$200,$A10,'Historias de Usuario'!$K$5:$K$200) -> 9 | G10: =IFERROR(F10/SUM($F$5:$F$12),0) -> 0.048128342
A11: EP-07 | B11: Reportes y analitica | C11: Informes de ingresos, ocupación y movimientos por rango de fechas, exportables. | D11: Que el administrador entienda como va su negocio con datos y no con percepción. | E11: =COUNTIF('Historias de Usuario'!$B$5:$B$200,$A11) -> 3 | F11: =SUMIF('Historias de Usuario'!$B$5:$B$200,$A11,'Historias de Usuario'!$K$5:$K$200) -> 13 | G11: =IFERROR(F11/SUM($F$5:$F$12),0) -> 0.069518717
A12: EP-08 | B12: Seguridad, auditoría y datos personales | C12: Capacidades transversales: consentimiento de tratamiento de datos, bitácora de auditoría de operaciones sensibles y ejercicio del derecho de supresión. | D12: Que el sistema sea defendible legal y técnicamente, y que toda operación sobre dinero o datos personales quede rastreada. | E12: =COUNTIF('Historias de Usuario'!$B$5:$B$200,$A12) -> 3 | F12: =SUMIF('Historias de Usuario'!$B$5:$B$200,$A12,'Historias de Usuario'!$K$5:$K$200) -> 13 | G12: =IFERROR(F12/SUM($F$5:$F$12),0) -> 0.069518717
A13: TOTAL | E13: =SUM(E5:E12) -> 47 | F13: =SUM(F5:F12) -> 187 | G13: =SUM(G5:G12) -> 1

Sheet Historias de Usuario
A1: Historias de usuario
A2: Una fila por historia, con su escenario de error. Las columnas Épica, MoSCoW, Puntos y Estado son listas desplegables. La columna Stakeholder cruza cada historia con el documento de Stakeholders v2.
A3: APAR-CAR v3.2 - Ficha 3229209. Historia de referencia: HU-04 (Cerrar mi sesión), anclada en 2 puntos.
A4: ID | B4: Épica | C4: Rol principal | D4: Titulo | E4: Como (rol) | F4: Quiero (acción) | G4: Para (beneficio) | H4: Criterios de aceptación (Dado / Cuando / Entonces) | I4: Escenario de error (Dado / Cuando / Entonces) | J4: MoSCoW | K4: Puntos | L4: Estado | M4: Dependencias | N4: Trazabilidad (RN / RNF / ADR) | O4: Stakeholder
A5: HU-01 | B5: EP-01 | C5: Persona nueva | D5: Registrarme como administrador con mi parqueadero | E5: persona nueva que administra un parqueadero | F5: crear mi cuenta indicando mis datos personales y los datos de mi parqueadero | G5: que el sistema cree mi parqueadero y me deje administrarlo desde el primer ingreso | H5: Dado que soy una persona nueva y elijo el tipo de cuenta administrador, cuando diligencio nombres, apellidos, correo, teléfono, contraseña y los datos de mi parqueadero (nombre, dirección, ubicación) y acepto la política de tratamiento de datos, entonces el sistema crea mi usuario, crea el parqueadero, me afilia a el con rol administrador y me permite iniciar sesión. | I5: Dado que el correo que ingreso ya está registrado, cuando intento crear la cuenta, entonces el sistema no la crea y me indica que ese correo ya existe, ofreciendome recuperar la contraseña. | J5: Must | K5: 5 | L5: Por hacer | M5: HU-35 | N5: RN-08, RN-09, RNF-01, RNF-03, RNF-05, ADR-001 | O5: -
A6: HU-02 | B6: EP-01 | C6: Persona nueva | D6: Registrarme como cliente | E6: persona nueva que usa un parqueadero | F6: crear mi cuenta con mis datos personales | G6: poder después vincularme a mi vehículo y consultar mi información | H6: Dado que soy una persona nueva y elijo el tipo de cuenta cliente, cuando diligencio mis datos y acepto la política de tratamiento de datos, entonces el sistema crea mi usuario sin afiliación y me lleva a la pantalla de vinculación de vehículo. | I6: Dado que dejo campos obligatorios vacíos o el correo tiene formato invalido, cuando intento registrarme, entonces el sistema señala cada campo con error y no crea la cuenta. | J6: Must | K6: 3 | L6: Por hacer | M6: HU-35 | N6: RN-08, RN-09, RNF-03, RNF-05 | O6: -
A7: HU-03 | B7: EP-01 | C7: Administrador / Operario / Cliente afiliado | D7: Iniciar sesión y ser dirigido según mi rol | E7: usuario registrado | F7: ingresar con mi correo y contraseña | G7: entrar directamente a la parte del sistema que me corresponde | H7: Dado que ingreso credenciales correctas, cuando presiono Iniciar sesión, entonces el sistema abre mi sesión y me dirige al panel que corresponde a mi rol: administrador, operario o cliente. El identificador del parqueadero queda fijado desde la sesión y no vuelve a pedirse. | I7: Dado que ingreso una contraseña incorrecta, cuando intento entrar, entonces el sistema muestra un mensaje genérico de credenciales invalidas sin revelar cual de los dos datos fallo, y bloquea el acceso temporalmente tras 5 intentos fallidos. | J7: Must | K7: 3 | L7: Por hacer | M7: HU-01, HU-02 | N7: RN-09, RNF-01, RNF-02, RNF-03, RNF-04, ADR-005 | O7: STK-01, STK-02, STK-03
A8: HU-04 | B8: EP-01 | C8: Administrador / Operario / Cliente afiliado | D8: Cerrar mi sesión | E8: usuario autenticado | F8: cerrar mi sesión de forma explicita | G8: evitar que otra persona use mi cuenta en un equipo compartido | H8: Dado que tengo una sesión abierta, cuando presiono Cerrar sesión, entonces el sistema invalida la sesión y me devuelve a la pantalla de ingreso. | I8: Dado que mi sesión ya fue invalidada, cuando intento volver a una pantalla interna con el boton atrás del navegador, entonces el sistema me redirige a la pantalla de ingreso y no muestra ningún dato. | J8: Must | K8: 2 | L8: Por hacer | M8: HU-03 | N8: RNF-02 | O8: STK-01, STK-02, STK-03
A9: HU-05 | B9: EP-01 | C9: Administrador / Operario / Cliente afiliado | D9: Recuperar mi contraseña | E9: usuario registrado que olvido su contraseña | F9: restablecerla mediante un enlace enviado a mi correo | G9: recuperar el acceso sin depender de nadie | H9: Dado que solicito recuperar mi contraseña con un correo registrado, cuando confirmo, entonces el sistema envía un enlace de un solo uso con vencimiento de 1 hora y permite definir una contraseña nueva. | I9: Dado que el enlace ya fue usado o ya venció, cuando intento abrirlo, entonces el sistema lo rechaza y me ofrece solicitar uno nuevo. | J9: Should | K9: 3 | L9: Por hacer | M9: HU-03 | N9: RN-09, RNF-01 | O9: STK-01, STK-02, STK-03
A10: HU-06 | B10: EP-01 | C10: Administrador / Operario / Cliente afiliado | D10: Actualizar mis datos de perfil | E10: usuario autenticado | F10: modificar mi teléfono, mi nombre y mi contraseña | G10: mantener mi información al día sin pedirle ayuda a nadie | H10: Dado que estoy autenticado, cuando modifico mis datos de perfil y guardo, entonces el sistema los actualiza y me confirma el cambio. | I10: Dado que intento cambiar mi contraseña, cuando no ingreso correctamente la contraseña actual, entonces el sistema rechaza el cambio y no modifica nada. | J10: Should | K10: 3 | L10: Por hacer | M10: HU-03 | N10: RNF-01, RNF-05 | O10: STK-01, STK-02, STK-03
A11: HU-07 | B11: EP-02 | C11: Administrador | D11: Registrar las celdas de mi parqueadero | E11: administrador | F11: dar de alta las celdas de mi parqueadero con un código y un tipo de vehículo permitido | G11: tener un inventario real de mi capacidad y no solo un número | H11: Dado que soy administrador, cuando registro una celda indicando su código (por ejemplo A-01) y el tipo permitido (carro, moto o mixta), entonces el sistema la guarda con estado Libre y la suma a mi capacidad total. El sistema permite también crear celdas en lote indicando un prefijo y una cantidad. | I11: Dado que intento registrar una celda con un código que ya existe en mi parqueadero, cuando guardo, entonces el sistema rechaza el registro e indica que ese código ya está en uso. | J11: Must | K11: 5 | L11: Por hacer | M11: HU-01 | N11: RN-01, ADR-003 | O11: STK-01
A12: HU-08 | B12: EP-02 | C12: Administrador / Operario | D12: Ver la ocupación de mis celdas en tiempo real | E12: administrador | F12: ver un tablero con cuales celdas están ocupadas y cuales libres en este momento | G12: saber de inmediato si tengo cupo para un vehículo que esta llegando | H12: Dado que tengo celdas registradas, cuando entro al tablero de ocupación, entonces veo cada celda con su estado actual, la placa que la ocupa cuando aplica, la hora de entrada, y los totales de libres y ocupadas. | I12: Dado que aún no he registrado ninguna celda, cuando entro al tablero, entonces el sistema me muestra un mensaje guiándome a registrarlas primero, con un enlace directo a esa pantalla. | J12: Must | K12: 5 | L12: Por hacer | M12: HU-07 | N12: RN-01, RNF-06 | O12: STK-01
A13: HU-09 | B13: EP-02 | C13: Administrador | D13: Definir y versionar mis tarifas | E13: administrador | F13: establecer el valor por hora, por día y por mensualidad, y cambiarlos cuando lo necesite | G13: que el sistema cobre siempre con la tarifa correcta sin que yo calcule nada | H13: Dado que soy administrador, cuando registro una tarifa indicando modalidad, valor y fecha de vigencia, entonces el sistema la guarda como una versión nueva sin borrar la anterior y la aplica a los movimientos que inicien desde esa fecha. Los vehículos que ya están adentro conservan la tarifa vigente al momento de su entrada. | I13: Dado que intento guardar una tarifa vacía, en cero o negativa, cuando confirmo, entonces el sistema no guarda y señala el campo con el error. | J13: Must | K13: 5 | L13: Por hacer | M13: HU-01 | N13: RN-02, RN-03, ADR-004 | O13: STK-01
A14: HU-10 | B14: EP-02 | C14: Administrador | D14: Editar los datos de mi parqueadero | E14: administrador | F14: actualizar el nombre, la dirección y la ubicación de mi parqueadero | G14: corregir errores del registro inicial o reflejar un cambio real | H14: Dado que soy administrador, cuando modifico los datos de mi parqueadero y guardo, entonces el sistema los actualiza y quedan reflejados en los documentos que se generen desde ese momento. | I14: Dado que dejo el nombre o la dirección en blanco, cuando intento guardar, entonces el sistema rechaza el cambio y conserva los datos anteriores. | J14: Should | K14: 3 | L14: Por hacer | M14: HU-01 | N14: RNF-08 | O14: STK-01
A15: HU-11 | B15: EP-02 | C15: Administrador | D15: Consultar el histórico de mis tarifas | E15: administrador | F15: ver todas las versiones de tarifa que he tenido con sus fechas de vigencia | G15: poder explicarle a un cliente por qué se le cobro un valor determinado | H15: Dado que he cambiado mis tarifas al menos una vez, cuando consulto el histórico, entonces veo cada versión con su modalidad, valor, fecha de vigencia y fecha de reemplazo. | I15: Dado que nunca he modificado mis tarifas, cuando consulto el histórico, entonces el sistema muestra únicamente la versión inicial e indica que no hay cambios posteriores. | J15: Could | K15: 3 | L15: Por hacer | M15: HU-09 | N15: RN-02, RNF-07 | O15: STK-01
A16: HU-12a | B16: EP-03 | C16: Administrador | D16: Registrar un cliente y su vehículo | E16: administrador | F16: dar de alta a un cliente con sus datos personales, la placa de su vehículo y su modalidad | G16: tener en el sistema quién usa mi parqueadero y en que condiciones | H16: Dado que soy administrador, cuando registro un cliente con sus datos de contacto, la placa de su vehículo y la modalidad (mensual o por horas), entonces el sistema normaliza la placa, crea la afiliación en estado Pendiente de vinculación y la asocia a mi parqueadero. La modalidad por horas identifica a un cliente afiliado que paga por tiempo; no debe confundirse con el cliente ocasional, que no tiene cuenta ni afiliación. | I16: Dado que la placa que ingreso ya está activa y vinculada a otro cliente en mi parqueadero, cuando intento guardar, entonces el sistema rechaza el registro e indica a que afiliación pertenece esa placa, sin revelar datos personales del otro cliente. | J16: Must | K16: 5 | L16: Por hacer | M16: HU-01 | N16: RN-04, RN-06, RNF-03, ADR-002 | O16: STK-01
... A51: HU-47 | B51: EP-05 | C51: Administrador | D51: Anular un pago registrado por error indicando el motivo | E51: administrador del parqueadero | F51: anular un pago que registre por error dejando escrito el motivo, y registrar el pago correcto aparte | G51: poder corregir un error de digitacion sin borrar el historial de dinero del cliente ni perder la cuenta de su cartera | H51: Dado un pago ya registrado, cuando lo anulo escribiendo el motivo, entonces el pago queda marcado como anulado sin borrarse (RN-13), se recalcula la fecha de vencimiento y el estado de cartera del cliente (RN-11, RN-12), y la anulacion queda en la bitacora con usuario, fecha, hora y motivo (RNF-07). / Dado un pago anulado, cuando consulto el historial de pagos del cliente, entonces aparece como anulado y no cuenta para el periodo vigente. / Dado que el valor registrado era incorrecto, cuando quiero corregirlo, entonces anulo el pago y registro uno nuevo, porque un pago no se edita ni se elimina. | I51: Dado que intento anular un pago sin escribir el motivo, cuando confirmo la operacion, entonces el sistema la rechaza, el pago permanece vigente y no se modifica ningun estado de cartera. | J51: Should | K51: 5 | L51: Por hacer | M51: HU-24 | N51: RN-11, RN-12, RN-13, RNF-07, RF-14, ADR-007 | O51: STK-01

Sheet Reglas de Negocio
A1: Reglas de negocio
A2: Condiciones que el sistema debe cumplir siempre, independientes de la pantalla. Se separan de las historias para no repetirlas en cada criterio de aceptación.
A4: ID | B4: Nombre | C4: Enunciado de la regla | D4: Historias que la aplican
A5: RN-01 | B5: Capacidad y celdas | C5: Cada celda pertenece a un único parqueadero, tiene un código único dentro de el y un tipo permitido (carro, moto o mixta). Una celda solo puede estar en estado Libre u Ocupada, y solo puede alojar un vehículo a la vez. | D5: HU-07, HU-08, HU-19, HU-20, HU-23, HU-33
A6: RN-02 | B6: Versionado de tarifas | C6: Una tarifa nunca se edita ni se borra: cada cambio crea una versión nueva con su fecha de vigencia. La versión anterior queda cerrada con fecha de reemplazo y permanece consultable. | D6: HU-09, HU-11, HU-21
A7: RN-03 | B7: Congelamiento de tarifa | C7: El movimiento guarda la referencia a la versión de tarifa vigente en el instante de la ENTRADA. El cobro de la salida se calcula siempre con esa versión, aunque la tarifa haya cambiado mientras el vehículo estuvo adentro. | D7: HU-09, HU-19, HU-20, HU-21
A8: RN-04 | B8: Formato y normalización de placa | C8: Antes de comparar o guardar, la placa se normaliza a mayúsculas y se le retiran espacios y guiones. Se valida contra el formato colombiano: AAA000 para automovil y AAA00A para motocicleta. La placa es única entre los vehículos ACTIVOS de un mismo parqueadero, no a nivel global del sistema. | D8: HU-12a, HU-13, HU-15, HU-19, HU-20
A9: RN-05 | B9: Código de vinculación | C9: El código de vinculación es alfanumérico de 6 caracteres, de un solo uso y vence a los 7 días calendario desde su emisión. Se invalida al usarse, al vencer, al generarse uno nuevo para la misma afiliación o tras tres intentos fallidos de vinculación. Se muestra una sola vez en pantalla y su emisión queda en la bitácora. | D9: HU-12b, HU-13, HU-17
A10: RN-06 | B10: La placa identifica, no autentica | C10: La placa por si sola NUNCA autoriza acceso a información. Toda vinculación exige placa más código emitido por el administrador. Ante un intento fallido el sistema no revela si la placa existe. | D10: HU-12a, HU-12b, HU-13, HU-15, HU-40
A11: RN-07 | B11: Vigencia del vínculo vehículo-cliente | C11: La relación entre un vehículo y una afiliación tiene fecha de inicio y fecha de fin. Al cambiar de dueño el vínculo se cierra, nunca se borra ni se reasigna. Cada movimiento pertenece al vínculo vigente en su fecha, de modo que el dueño anterior conserva su historial y el nuevo no lo ve. | D11: HU-16, HU-18, HU-28
A12: RN-08 | B12: Consentimiento de datos personales | C12: Ningún dato personal se almacena sin base de autorización. Cuando el titular se registra por si mismo, la autorización es explicita y no premarcada, y se guarda la constancia con fecha y versión del texto aceptado. Cuando los datos los captura un tercero dentro del sistema (el administrador al registrar un cliente en HU-12a o al crear un operario en HU-38), el responsable declara contar con la autorización del titular y el sistema exige al titular aceptar la política en su primer ingreso, antes de habilitarle cualquier función. Del cliente ocasional solo se registra la placa, que se trata como dato personal para efectos de supresión. La política debe informar por adelantado que, ante una solicitud de supresión, los registros de dinero se conservan anonimizados por trazabilidad contable y que la supresión no procede mientras exista un deber contractual vigente. | D12: HU-01, HU-02, HU-12a, HU-13, HU-20, HU-35, HU-37, HU-38
A13: RN-09 | B13: Credenciales | C13: Las contraseñas se almacenan únicamente como hash con sal. Nunca se guardan ni se transmiten en texto plano, y nunca se muestran ni se envían por correo. El mensaje de error de ingreso es genérico y no revela si el correo existe. | D13: HU-01, HU-02, HU-03, HU-05, HU-38, HU-46
A14: RN-10 | B14: Unicidad de presencia | C14: Una misma placa no puede tener dos movimientos abiertos simultáneos dentro del mismo parqueadero. Un movimiento se considera abierto mientras no tenga hora de salida. | D14: HU-19, HU-20, HU-21, HU-23
A15: RN-11 | B15: Ciclo de la mensualidad | C15: El período mensual es RODANTE. El primer pago de una afiliación inicia el período en su propia fecha y vence 30 días calendario después. A partir de ahí, un pago registrado antes del vencimiento encadena el período nuevo desde la fecha de vencimiento anterior y no desde la fecha de pago, de modo que el cliente no pierde los días que le quedaban. Un pago registrado después del vencimiento inicia un período nuevo en su propia fecha. Decisión cerrada en ADR-004; no hay prorrateo. | D15: HU-21, HU-24, HU-25, HU-29, HU-47
... A21: RN-17 | B21: Ciclo de vida del código QR del vehículo afiliado | C21: Cada vehículo afiliado tiene un único código QR activo a la vez. Se emite al registrar el vehículo y se entrega al titular, que lo conserva y lo porta consigo. El administrador puede revocarlo en cualquier momento por perdida, deterioro o cierre del vínculo vehículo-cliente; al revocarlo se puede emitir uno nuevo, y el anterior queda invalido de forma inmediata. La emisión, la entrega y la revocación quedan en la bitácora con usuario, fecha y motivo. Al cerrarse el vínculo por cambio de dueño según RN-07, el código se revoca automáticamente. | D21: HU-41, HU-42, HU-16, HU-18

Sheet Requisitos No Funcionales
A1: Requisitos no funcionales
A2: Cada uno trae su criterio de verificación: un RNF que no se puede verificar no es un requisito, es un deseo. La ultima columna cruza cada RNF con el riesgo que mitiga del documento Análisis de Seguridad en la Implantación de Software.
A4: ID | B4: Categoría | C4: Requisito | D4: Como se verifica | E4: Prioridad | F4: Relacionado con | G4: Riesgo que mitiga (Análisis de Seguridad)
A5: RNF-01 | B5: Seguridad - autenticación | C5: Contraseñas almacenadas como hash con sal mediante un algoritmo de derivación de clave reconocido. La sesión expira tras 30 minutos de inactividad. Tras 5 intentos fallidos consecutivos la cuenta queda bloqueada durante 15 minutos. El operario debe cambiar su contraseña inicial en el primer ingreso. | D5: Un intento de fuerza bruta de 100 combinaciones sobre una cuenta debe quedar bloqueado y registrado en la bitácora. | E5: Alta | F5: HU-01, HU-03, HU-05, HU-06, HU-38, HU-46 | G5: R2 - Robo de credenciales de usuario
A6: RNF-02 | B6: Seguridad - aislamiento entre parqueaderos | C6: El identificador del parqueadero se deriva SIEMPRE de la sesión autenticada, nunca de un parametro enviado por el cliente. Ninguna consulta puede devolver datos de un parqueadero distinto al de la sesión. | D6: El administrador del parqueadero A solicita un recurso del parqueadero B alterando el identificador en la petición y el sistema responde acceso denegado. | E6: Crítica | F6: Transversal a EP-01 a EP-08 | G6: R4 - Escalamiento de privilegios entre roles
A7: RNF-03 | B7: Seguridad - autorización por rol | C7: Cada operación valida rol y pertenencia EN EL SERVIDOR, no solo ocultando opciones en la interfaz. Matriz de permisos: el administrador accede a todo su parqueadero; el operario solo a ocupación, entrada, salida y vehículos adentro; el cliente solo a sus propios datos. Un cliente no puede acceder a datos de otro cliente ni a funciones de administrador, y un operario no puede acceder a tarifas, cartera, clientes, reportes ni bitácora. | D7: Tres pruebas: un cliente solicita el historial de otro cliente y recibe acceso denegado; un operario solicita el reporte de ingresos y recibe acceso denegado; ambos intentos quedan en la bitácora. | E7: Crítica | F7: HU-13, HU-19, HU-28, HU-30, HU-39, Transversal | G7: R4 - Escalamiento de privilegios entre roles
A8: RNF-04 | B8: Seguridad - transporte | C8: Toda comunicación sobre HTTPS. Ninguna credencial, código de vinculación, código de tiquete ni dato personal viaja en la URL ni queda en los registros del servidor. | D8: Inspección de tráfico y de logs sin encontrar credenciales, códigos ni datos personales en claro. | E8: Alta | F8: Transversal, HU-40 | G8: R2 - Robo de credenciales / R5 - Filtración de documentación
A9: RNF-05 | B9: Protección de datos personales | C9: Se recolecta el mínimo dato necesario. Del cliente ocasional no se captura ningún dato de contacto ni documento de identidad: solo la placa y un código de tiquete. La placa se trata como dato personal para efectos de supresión y nunca se muestra completa en pantallas públicas. Política de tratamiento publicada y aceptada de forma explicita. La supresión se atiende por anonimización, conservando los registros de dinero sin titular identificable (Ley 1581 de 2012 y Decreto 1377 de 2013, compilado en el Decreto 1074 de 2015). | D9: Un registro de cliente ocasional se completa sin capturar nombre, documento, teléfono ni correo; la consulta pública de HU-40 nunca devuelve la placa completa; una solicitud de supresión deja el registro de pago intacto y sin titular identificable. | E9: Alta | F9: HU-20, HU-27, HU-35, HU-37, HU-40, HU-43 | G9: R1 - Acceso no autorizado a la base de datos / R5
A10: RNF-06 | B10: Desempeño | C10: Las pantallas operativas de uso frecuente (ocupación, entrada, salida, vehículos adentro y listado de clientes) responden en menos de 2 segundos sobre un conjunto de datos de referencia de 60 celdas, 200 clientes afiliados y 12 meses de movimientos. | D10: Prueba de carga sobre el conjunto de datos de referencia midiendo el percentil 95 del tiempo de respuesta de las cinco pantallas indicadas. | E10: Media | F10: HU-08, HU-14, HU-23, HU-32, HU-33, HU-39 | G10: -
A11: RNF-07 | B11: Auditoría y trazabilidad | C11: Toda operación sobre dinero, tarifas, vinculaciones, cuentas de operario y datos personales queda en una bitácora solo anexable (se escribe y se consulta, pero ningún registro se modifica ni se elimina) con usuario, fecha y hora. Las operaciones que corrigen o revierten un hecho ya registrado (anulaciones y correcciones de movimiento) exigen además un motivo escrito. Ningún rol puede modificar ni eliminar la bitácora. | D11: Ejecutar una anulación y verificar que el evento aparece en la bitácora y que ningún rol logra modificarlo. | E11: Alta | F11: HU-11, HU-16, HU-17, HU-22, HU-26, HU-34, HU-36, HU-37, HU-38, HU-39, HU-46, HU-47 | G11: R1 - Acceso no autorizado / R4 - Escalamiento de privilegios
A12: RNF-08 | B12: Usabilidad | C12: Ni el administrador ni el operario objetivo son personas con formación técnica. Registrar una entrada y registrar una salida deben completarse en no más de cinco pasos cada una y sin capacitación previa. | D12: Prueba con 3 usuarios sin formación técnica: al menos 2 completan ambas tareas sin ayuda, dentro del limite de cinco pasos y sin errores que impidan terminar. | E12: Alta | F12: HU-10, HU-19, HU-20, HU-21, HU-39 | G12: -
A13: RNF-09 | B13: Disponibilidad y respaldo | C13: Respaldo automático diario de la base de datos con retención de 30 días y procedimiento de restauración probado al menos una vez antes de la entrega. | D13: Ejecutar una restauración completa desde un respaldo y verificar la integridad de los datos. | E13: Media | F13: Transversal | G13: R1 - Pérdida o alteración de la base de datos
A14: RNF-10 | B14: Seguridad - gestión del código fuente | C14: El repositorio permanece privado durante todo el proyecto. Ninguna credencial, clave de conexión ni dato real de prueba se versiona: la configuración sensible se maneja por variables de entorno y el archivo de ejemplo se pública sin valores. Se revisa el historial antes de cada entrega. | D14: Revisión del repositorio y de su historial de commits sin encontrar credenciales ni cadenas de conexión; verificación de que la visibilidad es privada. | E14: Media | F14: Transversal al proyecto | G14: R3 - Filtración del código fuente
A15: RNF-11 | B15: Seguridad - dispositivo lector | C15: El dispositivo lector se autentica ante la API con una clave propia de dispositivo, revocable desde el sistema y distinta de las credenciales de cualquier persona. Envía únicamente el código leido y el identificador del punto de lectura, siempre sobre HTTPS y en el cuerpo de la petición, nunca en la URL. Un lector no autenticado, revocado o desconocido es rechazado y el intento queda en la bitácora. La indisponibilidad del lector no bloquea la operación: el registro manual permanece habilitado en todo momento. | D15: Se envía una lectura desde un dispositivo sin clave valida y el sistema responde acceso denegado dejando el intento en la bitácora; se desconecta el lector y el operario completa una entrada y una salida por la vía manual. | E15: Alta | F15: HU-43, HU-44, HU-45, RN-16 | G15: R2 - Robo de credenciales
A16: Nota: el ultimo requisito es nuevo en la v3.0. El riesgo R3 del Análisis de Seguridad (filtración del código fuente) no estaba cubierto por ningún requisito verificable.

Sheet INVEST
A1: Checklist INVEST por historia
A2: Independiente / Negociable / Valiosa / Estimable / Small / Testeable. El criterio I se evalua como ENTREGABLE de forma independiente, no como construible en cualquier orden: se marca Revisar únicamente cuando la historia no aporta valor por si sola sin otra. Una observación escrita vale más que un Si sin sustento.
A4: ID | B4: Titulo | C4: I | D4: N | E4: V | F4: E | G4: S | H4: T | I4: Observación
A5: HU-01 | B5: Registrarme como administrador con mi parqueadero | C5: Si | D5: Si | E5: Si | F5: Si | G5: Si | H5: Si
A6: HU-02 | B6: Registrarme como cliente | C6: Si | D6: Si | E6: Si | F6: Si | G6: Si | H6: Si
A7: HU-03 | B7: Iniciar sesión y ser dirigido según mi rol | C7: Si | D7: Si | E7: Si | F7: Si | G7: Si | H7: Si
A8: HU-04 | B8: Cerrar mi sesión | C8: Si | D8: Si | E8: Si | F8: Si | G8: Si | H8: Si
A9: HU-05 | B9: Recuperar mi contraseña | C9: Si | D9: Si | E9: Si | F9: Si | G9: Si | H9: Si
A10: HU-06 | B10: Actualizar mis datos de perfil | C10: Si | D10: Si | E10: Si | F10: Si | G10: Si | H10: Si
A11: HU-07 | B11: Registrar las celdas de mi parqueadero | C11: Si | D11: Si | E11: Si | F11: Si | G11: Si | H11: Si
A12: HU-08 | B12: Ver la ocupación de mis celdas en tiempo real | C12: Si | D12: Si | E12: Si | F12: Si | G12: Si | H12: Si
A13: HU-09 | B13: Definir y versionar mis tarifas | C13: Si | D13: Si | E13: Si | F13: Si | G13: Si | H13: Si
A14: HU-10 | B14: Editar los datos de mi parqueadero | C14: Si | D14: Si | E14: Si | F14: Si | G14: Si | H14: Si
A15: HU-11 | B15: Consultar el histórico de mis tarifas | C15: Si | D15: Si | E15: Si | F15: Si | G15: Si | H15: Si
A16: HU-12a | B16: Registrar un cliente y su vehículo | C16: Si | D16: Si | E16: Si | F16: Si | G16: Si | H16: Si | I16: Resuelto en la v3.0: la antigua HU-12 de 8 puntos se dividió. Esta mitad entrega valor por si sola porque el administrador ya tiene su lista de clientes aunque el código todavía no exista.
A17: HU-12b | B17: Generar el código de vinculación de un cliente | C17: Revisar | D17: Si | E17: Si | F17: Si | G17: Si | H17: Si | I17: Depende de HU-12a en el orden de construcción, pero se entrega y se prueba de forma independiente.
A18: HU-13 | B18: Vincular mi cuenta a mi vehículo con placa y código | C18: Si | D18: Si | E18: Si | F18: Si | G18: Si | H18: Si
A19: HU-14 | B19: Ver y filtrar la lista de mis clientes afiliados | C19: Si | D19: Si | E19: Si | F19: Si | G19: Si | H19: Si
A20: HU-15 | B20: Asociar un segundo vehículo a un cliente ya afiliado | C20: Si | D20: Si | E20: Si | F20: Si | G20: Si | H20: Si
A21: HU-16 | B21: Cerrar la vinculación de un vehículo por cambio de dueño | C21: Si | D21: Si | E21: Si | F21: Si | G21: Si | H21: Si
A22: HU-17 | B22: Reenviar o regenerar un código de vinculación | C22: Si | D22: Si | E22: Si | F22: Si | G22: Si | H22: Si | I22: Reclasificada a Must en la v3.0: es el único camino de recuperación cuando el código se pierde, se bloquea tras 3 intentos o vence a los 7 días. Sin ella, un cliente bloqueado no puede vincularse nunca.
A23: HU-18 | B23: Desactivar un cliente | C23: Si | D23: Si | E23: Si | F23: Si | G23: Si | H23: Si
A24: HU-19 | B24: Registrar la entrada de un vehículo afiliado | C24: Si | D24: Si | E24: Si | F24: Si | G24: Si | H24: Si | I24: Depende de HU-07, HU-09 y HU-12a en el orden de construcción, pero entrega valor por si sola: registrar un ingreso ya sustituye el cuaderno.
A25: HU-20 | B25: Registrar la entrada de un visitante ocasional | C25: Si | D25: Si | E25: Si | F25: Si | G25: Si | H25: Si
A26: HU-21 | B26: Registrar la salida y calcular el cobro automáticamente | C26: Si | D26: Si | E26: Si | F26: Si | G26: Revisar | H26: Si | I26: 8 puntos, la historia más grande del backlog. Se mantiene UNIDA por decisión del equipo (14/08/2026): dividirla en cerrar movimiento y calcular cobro dejaría una primera mitad que libera la celda sin cobrar nada, lo cual no es un incremento entregable. Concentra RN-03, RN-10, RN-14 y RN-15.
A27: HU-22 | B27: Anular o corregir un movimiento mal registrado | C27: Si | D27: Si | E27: Si | F27: Si | G27: Si | H27: Si
A28: HU-23 | B28: Consultar que vehículos están adentro en este momento | C28: Si | D28: Si | E28: Si | F28: Si | G28: Si | H28: Si
A29: HU-24 | B29: Registrar el pago de una mensualidad | C29: Si | D29: Si | E29: Si | F29: Si | G29: Si | H29: Si
A30: HU-25 | B30: Ver el estado de cartera de mis clientes | C30: Si | D30: Si | E30: Si | F30: Si | G30: Si | H30: Si
A31: HU-26 | B31: Consultar el historial de pagos de un cliente | C31: Si | D31: Si | E31: Si | F31: Si | G31: Si | H31: Si
A32: HU-27 | B32: Generar carta de cobro en PDF | C32: Si | D32: Si | E32: Si | F32: Si | G32: Si | H32: Si
A33: HU-28 | B33: Ver el historial de entradas y salidas de mi vehículo | C33: Si | D33: Si | E33: Si | F33: Si | G33: Si | H33: Si
A34: HU-29 | B34: Ver el estado de mi mensualidad | C34: Si | D34: Si | E34: Si | F34: Si | G34: Si | H34: Si
A35: HU-30 | B35: Consultar mis pagos registrados | C35: Si | D35: Si | E35: Si | F35: Si | G35: Si | H35: Si
A36: HU-32 | B36: Generar el reporte de ingresos por rango de fechas | C36: Si | D36: Si | E36: Si | F36: Si | G36: Si | H36: Si
A37: HU-33 | B37: Generar el reporte de ocupación | C37: Si | D37: Si | E37: Si | F37: Si | G37: Si | H37: Si
A38: HU-34 | B38: Generar el reporte de vehículos y movimientos | C38: Si | D38: Si | E38: Si | F38: Si | G38: Si | H38: Si
... A40: HU-36 | B40: Consultar la bitácora de auditoría de mi parqueadero | C40: Si | D40: Si | E40: Si | F40: Si | G40: Si | H40: Si
A41: HU-37 | B41: Solicitar la eliminación de mis datos personales | C41: Si | D41: Si | E41: Si | F41: Si | G41: Si | H41: Si | I41: Resuelto en la v3.0: la historia pasa de eliminar a inhabilitar y luego anonimizar (ADR-007), con lo cual el alcance queda cerrado y la historia es estimable y testeable.
A42: HU-38 | B42: Registrar un operario para mi parqueadero | C42: Si | D42: Si | E42: Si | F42: Si | G42: Si | H42: Si
A43: HU-39 | B43: Ingresar a mi panel de operación con acceso restringido | C43: Revisar | D43: Si | E43: Si | F43: Si | G43: Si | H43: Si | I43: Depende de HU-38. Su valor esta sobre todo en lo que NIEGA, así que su prueba principal son los intentos de acceso denegados, no la vista en si.
A44: HU-40 | B44: Consultar mi tiquete con el código de entrada | C44: Revisar | D44: Si | E44: Si | F44: Si | G44: Si | H44: Si | I44: No aporta valor sin el código que genera HU-20, por eso se marca Revisar en I. Es la única historia con una pantalla pública sin autenticación, de modo que su escenario de error pesa tanto como su criterio de aceptación.
A45: HU-46 | B45: Ser informado cuando mi cuenta queda bloqueada por intentos fallidos | C45: Si | D45: Si | E45: Si | F45: Si | G45: Si | H45: Si | I45: Depende de HU-03 para tener sesion, pero se construye y se prueba aparte. Verificable con un guion de cinco intentos fallidos.
A46: HU-47 | B46: Anular un pago registrado por error indicando el motivo | C46: Si | D46: Si | E46: Si | F46: Si | G46: Si | H46: Si | I46: Misma forma que HU-22 para movimientos. El recalculo de cartera es la parte que concentra el esfuerzo.

Sheet Trazabilidad
A1: Matriz de trazabilidad
A2: Cadena Necesidad -> Stakeholder -> Épica -> Historia -> Regla o RNF -> Caso de prueba. La ultima columna se completa en la fase de Pruebas y ajustes (01/12/2026 - 22/12/2026 según el cronograma del Acta de Constitución).
A4: ID | B4: Necesidad del negocio | C4: Origen | D4: Stakeholder | E4: Épicas | F4: Historias | G4: Reglas / RNF | H4: Casos de prueba
A5: NEC-01 | B5: Eliminar el control manual en papel de las entradas y salidas de vehículos | C5: Acta de Constitución, Antecedentes y Justificación | D5: STK-01, STK-02 | E5: EP-02, EP-04 | F5: HU-07, HU-08, HU-19, HU-20, HU-21, HU-23, HU-43, HU-44, HU-45 | G5: RN-01, RN-10, RN-16, RNF-08, RNF-11 | H5: Por definir
A6: NEC-02 | B6: Cobrar el valor exacto sin cálculos manuales ni discusiones con el cliente | C6: Acta de Constitución, Objetivo Específico 5 | D6: STK-01, STK-03 | E6: EP-02, EP-04 | F6: HU-09, HU-11, HU-21, HU-22 | G6: RN-02, RN-03, RN-13, RN-14 | H6: Por definir
A7: NEC-03 | B7: Saber en todo momento quién está al día y quién está en mora, y poder cobrar a tiempo | C7: Acta de Constitución, Objetivo Específico 5 | D7: STK-01 | E7: EP-05 | F7: HU-24, HU-25, HU-26, HU-27, HU-47 | G7: RN-11, RN-12, RN-13 | H7: Por definir
A8: NEC-04 | B8: Dar transparencia al cliente sobre su propio uso y su estado de cuenta | C8: Acta de Constitución, Objetivo Específico 6 | D8: STK-03 | E8: EP-06 | F8: HU-28, HU-29, HU-30 | G8: RN-07, RN-12, RNF-03 | H8: Por definir
A9: NEC-05 | B9: Entender el desempeño del negocio con datos y no con percepción | C9: Acta de Constitución, Objetivo Específico 7 | D9: STK-01 | E9: EP-07 | F9: HU-32, HU-33, HU-34 | G9: RN-13, RNF-06 | H9: Por definir
A10: NEC-06 | B10: Permitir que varios parqueaderos independientes usen la plataforma sin verse entre si | C10: Acta de Constitución, Alcance Incluido + ADR-001 | D10: STK-01 | E10: EP-01, EP-03 | F10: HU-01, HU-02, HU-03, HU-12a, HU-12b, HU-13, HU-14 | G10: RN-04, RN-05, RN-06, RNF-02 | H10: Por definir
A11: NEC-07 | B11: Cumplir la protección de datos personales y poder auditar toda operación sobre dinero | C11: Análisis de Seguridad (R1, R4, R5) + Ley 1581 de 2012 | D11: STK-01, STK-03 | E11: EP-08 | F11: HU-22, HU-35, HU-36, HU-37 | G11: RN-08, RN-09, RN-13, RNF-05, RNF-07 | H11: Por definir
A12: NEC-08 | B12: Permitir que el operario de turno registre los movimientos sin ver información del negocio que no le corresponde | C12: Acta de Constitución, Objetivo General y Específico 2 + Stakeholders STK-02 | D12: STK-01, STK-02 | E12: EP-01, EP-04 | F12: HU-03, HU-19, HU-20, HU-21, HU-23, HU-38, HU-39, HU-43, HU-44, HU-45 | G12: RN-09, RNF-02, RNF-03, RNF-07, RNF-08 | H12: Por definir
A13: NEC-09 | B13: Atender al cliente de paso sin obligarlo a registrarse y dejarlo consultar lo que va a pagar | C13: Stakeholders STK-04, Necesidad y Expectativa | D13: STK-04 | E13: EP-04 | F13: HU-20, HU-21, HU-40 | G13: RN-06, RN-14, RN-15, RNF-05 | H13: Por definir
A14: NEC-10 | B14: Proteger el código fuente y la documentación generada por el sistema | C14: Análisis de Seguridad (R3, R5) | D14: STK-05 | E14: Transversal | F14: HU-27, HU-36 | G14: RNF-04, RNF-07, RNF-10 | H14: Por definir
A15: NEC-11 | B15: Mantener al día la información del parqueadero y de las afiliaciones a lo largo del tiempo: segundo vehículo, cambio de dueño y retiro de un cliente | C15: Acta de Constitución, Objetivo Específico 1 (modelo de datos) | D15: STK-01 | E15: EP-02, EP-03 | F15: HU-10, HU-15, HU-16, HU-17, HU-18, HU-41, HU-42 | G15: RN-04, RN-06, RN-07, RNF-07, RNF-08 | H15: Por definir
A16: NEC-12 | B16: Que cada usuario gestione su propio acceso y sus credenciales sin depender de otra persona | C16: Acta de Constitución, Objetivo Específico 2 (autenticación y autorización) | D16: STK-01, STK-02, STK-03 | E16: EP-01 | F16: HU-04, HU-05, HU-06, HU-46 | G16: RN-09, RNF-01, RNF-04 | H16: Por definir

Sheet Decisiones (ADR)
A1: Decisiones de arquitectura registradas
A2: Una decisión sin alternativas evaluadas no es un ADR, es una nota. Las siete decisiones de reglas de negocio y de arquitectura funcional están Aceptadas: al 14/08/2026 no queda ninguna decisión de negocio abierta. Queda pendiente ADR-008 sobre el stack tecnológico (lenguaje de servidor y framework), que se registra en la fase de Diseño y arquitectura.
A4: ID | B4: Decisión | C4: Estado | D4: Contexto (que problema resuelve) | E4: Decisión tomada | F4: Alternativas evaluadas y descartadas | G4: Consecuencias
A5: ADR-001 | B5: Estrategia de multi-tenencia | C5: Aceptada | D5: Se quiere poder ofrecer la plataforma a varios parqueaderos independientes, cada uno con su propio administrador, sin reinstalar el sistema para cada uno. El Acta de Constitución lo confirma: el sistema permitirá administrar uno o varios parqueaderos. | E5: Base de datos compartida con discriminador de inquilino: cada tabla operativa lleva parqueadero_id y toda consulta se filtra por el identificador derivado de la sesión. | F5: 1) Una instalación separada por parqueadero: descartada porque cada cliente nuevo exige un despliegue manual y multiplica el mantenimiento. 2) Una base de datos por parqueadero: descartada por complejidad de migraciones y respaldos para el tamaño del equipo. | G5: El sistema soporta N parqueaderos desde el día uno y funciona igual con N=1. Obliga a implementar RNF-02 desde el inicio: un filtro olvidado expone datos de otro parqueadero.
A6: ADR-002 | B6: Mecanismo de vinculación cliente-vehículo-parqueadero | C6: Aceptada | D6: Un cliente que se registra por su cuenta no tiene forma de indicar a que parqueadero pertenece, y el administrador tampoco puede confiar en que la placa que alguien declare sea suya. | E6: Vinculación por placa más código de 6 caracteres emitido por el administrador. El registro del administrador es la fuente de verdad; el cliente solo activa. | F6: 1) Invitación por correo: descartada porque muchos clientes de parqueaderos pequeños no le dan correo al administrador. 2) Autovinculación solo con la placa: descartada porque la placa es pública y cualquiera podría reclamar un vehículo ajeno. | G6: Elimina los duplicados por construcción y resuelve también a que parqueadero se vincula el cliente, porque el código ya pertenece a un parqueadero. Exige gestionar vencimiento y regeneración de códigos (HU-12b, HU-17).
A7: ADR-003 | B7: Modelo de espacios: celdas identificadas | C7: Aceptada (confirmada 14/08/2026) | D7: El backlog v1 guardaba un número total de espacios pero pedía mostrar cuales estaban ocupados, lo cual es imposible con un contador. | E7: Inventario de celdas identificadas con código propio (A-01, A-02) y tipo de vehículo permitido. Confirmado por el Acta de Constitución, que habla expresamente de celdas identificadas y de asociar cada movimiento a una placa y a una celda. | F7: Contador simple de cupos disponibles: más fácil de implementar, pero impide el tablero de ocupación, la asignación de celda al ingreso y el reporte de ocupación por franja. | G7: Habilita HU-08, HU-19, HU-20 y HU-33 tal como están escritas. Costo adicional estimado: 2 a 3 puntos. Se elimina el supuesto SUP-01 de la v2.
A8: ADR-004 | B8: Ciclo de facturación rodante | C8: Aceptada (confirmada 14/08/2026) | D8: No estaba definido cuando inicia y cuando termina el período mensual de un cliente, lo que dejaba las historias de cartera sin criterio verificable. | E8: Período rodante de 30 días calendario desde la fecha del pago, encadenado desde el vencimiento anterior cuando el cliente paga antes de vencerse. | F8: Corte fijo mensual el día 1: más alineado con la contabilidad tradicional, pero exige prorrateo para quien se afilia a mitad de mes, lo que agrega una regla de cálculo adicional y es la fuente de error más comun en este tipo de sistemas. | G8: Simplifica RN-11 y RN-12 y elimina la necesidad de prorrateo. Se elimina el supuesto SUP-02 de la v2. Si el negocio real llegara a exigir corte fijo, cambia RN-11 y afecta HU-24, HU-25 y HU-29. Nota de contexto (09/09/2026): esta decisión se definio sobre el caso general del segmento al que se dirige la plataforma y no se derivo del parqueadero de referencia, cuya práctica actual es fecha fija de pago dentro del mes calendario, con la lista de clientes reescrita a mano cada mes en tres segmentos (1-10, 10-20 y 20-30). La diferencia es deliberada y busca la replicabilidad del producto.
A9: ADR-005 | B9: Inclusión del rol operario en la primera versión | C9: Aceptada (14/08/2026) | D9: El backlog v2 dejaba el rol de operario fuera de alcance, pero el Acta de Constitución lo promete en el objetivo general, en el objetivo específico 2 y en el Entregable 5 (mockups de los tres paneles), y el documento de Stakeholders lo clasifica como STK-02, usuario clave con interes alto. Era una contradicción entre entregables del mismo proyecto, justamente el riesgo que STK-06 califica de impacto alto. | E9: El operario entra a la primera versión como tercer rol. Se implementa como un valor más del rol de la afiliación ya modelada en ADR-001, con permisos restringidos a ocupación, entrada, salida y vehículos adentro. | F9: 1) Sacar el operario del Acta: descartada porque obliga a reescribir un documento ya entregado y fechado, y a renunciar a un entregable comprometido. 2) Dejarlo para una segunda versión: descartada porque el operario es el usuario real del sistema en la caseta; sin el, la plataforma describe una realidad que el propio Acta documenta y luego ignora. | G9: Suma HU-38 y HU-39 (8 puntos) y amplia HU-03, HU-19, HU-20, HU-21 y HU-23. Convierte RNF-03 en un requisito verificable con casos concretos en lugar de una declaración genérica. Se elimina la fila de operario de la hoja Fuera de alcance.
A10: ADR-006 | B10: Algoritmo de cobro por bloques de 24 horas | C10: Aceptada (14/08/2026) | D10: La v2 proponía redondear la fracción a la hora superior y aplicar tarifa día a partir de un umbral fijo de 12 horas. Con cobro proporcional ese umbral produce cobros superiores a la tarifa día: con 3.000 por hora y 25.000 por día, el punto de equilibrio real esta en 8,3 horas, de modo que una estadía de 10 horas cobraría 30.000. Además no había ninguna regla para estadías de varios días. | E10: Cobro por bloques de 24 horas desde la entrada. Por bloque se cobra el menor entre el proporcional por minuto y la tarifa día. Cobro mínimo total de una hora. El umbral deja de ser un número fijo y se deduce solo de las tarifas de cada administrador. | F10: 1) Redondeo a la hora superior: descartada por ser menos justa y más difícil de explicarle al cliente. 2) Umbral fijo de 12 horas: descartada porque cobra de más entre el punto de equilibrio y el umbral, y porque el punto de equilibrio cambia con las tarifas de cada parqueadero. 3) Umbral configurable por el administrador: descartada por agregar un parametro que se puede calcular solo. | G10: RN-14 queda cerrada y verificable con casos concretos: 5 minutos cobran 3.000; 2 horas 20 minutos cobran 7.000; 10 horas cobran 25.000; 3 días y 2 horas cobran 81.000. La regla funciona con cualquier tarifa y nunca cobra por encima de la tarifa día. Los valores en dinero los sigue definiendo cada administrador en HU-09. La exención del cliente mensual vigente queda escrita en la propia regla, para que HU-21 no le cobre la estadía a quien ya pago su período. Nota de contexto (09/09/2026): el parqueadero de referencia no tiene hoy tarifa definida para el visitante ocasional: se cobra por días el valor que el administrador decide en el momento. El algoritmo es por tanto capacidad nueva que el sistema introduce y no la automatización de una práctica existente.
A11: ADR-007 | B11: Inhabilitación y anonimización en lugar de eliminación de datos | C11: Aceptada (14/08/2026) | D11: El derecho de supresión de la Ley 1581 de 2012 choca con RN-13, que declara inmutables los registros de dinero: borrar a un cliente dejaría sus pagos huérfanos y rompería la contabilidad y la auditoría del administrador. | E11: Dos estados. Mientras exista una obligación vigente (mensualidad activa, saldo pendiente o vehículo adentro), la solicitud queda En espera y la afiliación se inhabilita de la operación diaria conservando los datos, amparada en el deber contractual que reconoce el Decreto 1377 de 2013 (artículo compilado en el Decreto 1074 de 2015): la supresión no procede cuando el titular tiene un deber legal o contractual de permanecer en la base de datos. Terminada la obligación, la solicitud se ejecuta por anonimización: los datos identificables se reemplazan por marcadores neutros y el registro financiero sobrevive sin titular. | F11: 1) Eliminación física del registro: descartada porque destruye la trazabilidad contable exigida por RN-13 y RNF-07. 2) Negar siempre la supresión apoyandose en los términos y condiciones: descartada porque un contrato no puede renunciar a un derecho legal; la excepción la da la norma, no el contrato, y es temporal mientras dure la obligación. 3) Inhabilitar sin anonimizar nunca: descartada porque en la práctica el derecho de supresión no existiria. | G11: Reescribe HU-37 y amplia RN-08: la política de tratamiento debe informar por adelantado que los registros de dinero se conservan anonimizados. Requiere validación del enfoque con el instructor antes de la sustentación.
A12: ADR-008 | B12: Selección del lenguaje de servidor y del motor de persistencia | C12: Aceptada (11/09/2026) | D12: El Acta de Constitución lista MySQL, XAMPP, Visual Studio Code, GitHub y Figma como recursos disponibles del equipo, no como obligación del proyecto. Hasta la v3.2 ninguna decisión registrada justificaba una elección de stack, y la numeración del libro saltaba de ADR-007 a ADR-009. Lo que si es restricción es que el producto sea web responsivo, que el código viva en control de versiones y que el equipo pueda explicar toda tecnología que incorpore. | E12: JavaScript en todo el proyecto. Servidor: Node.js 22 LTS con Express. Cliente: React 18 con Vite y Bootstrap 5 mediante react-bootstrap. Persistencia: PostgreSQL gestionado en Neon, con Prisma como ORM. Autenticacion: sesion en servidor con express-session, almacenada en PostgreSQL, y bcrypt para el hash de la contrasena. Despliegue: dos proyectos en Vercel sobre un mismo repositorio, con /api/* del dominio del cliente redirigido al servidor. Documentacion y pruebas manuales de la API: coleccion de Postman publicada. Pruebas automatizadas: Vitest con Supertest. Analisis estatico: SonarCloud, ESLint y Prettier. Manejo de fechas: toda marca de tiempo se almacena como timestamptz en UTC y se convierte a America/Bogota solo al presentarla, porque de ello dependen RN-14 (bloques de 24 horas) y RN-11 (vencimiento a 30 dias). | F12: 1) PHP 8.3 con Laravel: viable y la lectura literal de los recursos del Acta (MySQL y XAMPP); descartada porque es el framework con mas convencion que el equipo tendria que justificar en la sustentacion y ninguno de los tres integrantes lo ha usado. 2) Python 3.12 con FastAPI: descartada porque exige montar a mano las sesiones, el bloqueo por intentos y el aislamiento multi-inquilino. 3) SQL Server como motor: descartada porque Prisma no soporta enums en ese motor, y el modelo usa enumeraciones en los cuatro estados de cartera de RN-12, en el origen del movimiento y en el estado del codigo QR; suma la limitacion de un solo valor nulo por restriccion UNIQUE, que afecta el vinculo vehiculo-cliente con fecha de fin nula. 4) TypeScript: mejor herramienta, descartada porque es un lenguaje mas que aprender sobre React, Express, Prisma y el firmware del lector, y nada de lo prometido lo exige. 5) Better Auth para la autenticacion: descartada porque esta pensada para TypeScript, trae su propio esquema de tablas que habria que conciliar con la tabla de usuarios, y su limitador cuenta peticiones por direccion IP, que no es el bloqueo de cuenta que exige RNF-01. 6) Tailwind CSS: descartada porque no aporta componentes y obligaria a construir desde cero cada tabla, modal y menu de los tres paneles. 7) Vistas renderizadas en el servidor con plantillas: ver ADR-010. | G12: Cierra el pendiente 3 de la v3.3 y desbloquea la verificacion arquitectonica de P04. Se aparta de los recursos que lista el Acta (MySQL y XAMPP): la desviacion queda justificada aqui, del mismo modo que ADR-009 justifico el lector frente a la exclusion de hardware. Obliga a registrar ADR-010 y a corregir el apartado A.1 de P04. Agrega las historias tecnicas HT-05 a HT-08. Los criterios de verificacion de los RNF no cambian, solo su implementacion: RNF-01 con express-session y bcrypt mas el bloqueo de HU-46, RNF-02 con extensiones de cliente de Prisma que centralizan el filtro por parqueadero_id, y RNF-11 contra un endpoint sin estado. El despliegue es serverless aunque el codigo sea monolitico, de modo que la sesion no puede vivir en memoria del proceso ni la imagen del codigo QR en el sistema de archivos: se genera al vuelo. La metrica MET-03 de la P06 (cobertura de pruebas) solo la produce Vitest, no Postman. La decision se toma sobre planes gratuitos y debe validarse con el instructor antes de iniciar la construccion.
A13: ADR-009 | B13: Registro de movimientos mediante lector físico de código QR | C13: Aceptada (28/08/2026) | D13: La Formulación del proyecto anuncia en Funciones Generales Incluidas que la entrada y la salida se registran por medio del QR, pero el mismo documento excluye la integración con hardware y declara como limitación que la exactitud del registro depende de que el operario digite la placa. El backlog, el documento de Alcance y las 40 historias recogieron la exclusión y no el QR. La contradicción debía resolverse en un sentido o en el otro antes de modelar los procesos y los diagramas de comportamiento. | E13: Se incorpora al alcance de la v1 un lector físico propio, construido por el equipo sobre un microcontrolador ESP32 con modulo lector de código QR, que envía la lectura a un endpoint de la API. El lector no decide: identifica al vehículo y el operario confirma la placa antes de cerrar el movimiento (RN-16). Cada vehículo afiliado recibe un código QR portatil que conserva su titular, y el cliente ocasional recibe su tiquete impreso como código QR (RN-17, RN-15). El registro manual permanece habilitado como vía alterna permanente. Se retira en consecuencia la exclusión de integración con hardware del parqueadero. | F13: Lectura por camara del navegador: descartada porque obliga al operario a manipular un dispositivo personal en cada movimiento y no aporta la agilidad buscada en hora pico. Lector comercial de gama industrial: descartado por costo, contradice la premisa de solución de bajo costo del Acta. Reconocimiento automático de placa por camara: ya estaba descartado por complejidad y sigue diferido a una segunda fase. Mantener solo digitación manual: descartado porque contradice la función anunciada en la Formulación y desaprovecha una mejora real del tiempo de atención. | G13: Amplia el alcance frente al Acta de Constitución, lo que activa el riesgo de mayor probabilidad e impacto identificado allí; por eso la decisión queda registrada por escrito y con control de cambios en los cuatro artefactos. Agrega RF-21, RF-22, RN-16, RN-17, RNF-11 y las historias HU-41 a HU-45. Obliga a disponer del hardware y a probarlo antes de la sustentación. El riesgo se acota con el registro manual: si el lector no está listo, el producto sigue siendo demostrable en su totalidad.
A14: ADR-010 | B14: Estilo arquitectonico del producto | C14: Aceptada (11/09/2026) | D14: La plantilla P04 contrasta los ocho diagramas de secuencia y de actividades contra una decision ADR-010 que nunca existio en el libro: el estilo se habia conversado en el equipo y no se escribio, el mismo patron que se corrigio con el catalogo de requisitos funcionales en la v3.2. Ademas, la eleccion de React en ADR-008 cambia el estilo respecto de lo que P04 describia, porque el servidor deja de renderizar vistas. | E14: Monolito modular con cliente desacoplado. El servidor concentra en un solo despliegue y una sola base de codigo las capas de aplicacion (CMP-02), dominio (CMP-03) y persistencia (CMP-04 y CMP-05), con las reglas de negocio unicamente en la capa de dominio y sin saltos de capa: la aplicacion solo habla con el dominio y el dominio solo con la persistencia. La presentacion (CMP-01) se construye como aplicacion de una sola pagina en React, se despliega por separado y se comunica con el servidor exclusivamente por la API HTTP. No hay patron modelo-vista-controlador, porque el servidor no devuelve vistas. El lector de codigo QR (EXT-01) es un participante externo que se comunica unicamente con la capa de aplicacion y se autentica con clave propia de dispositivo (RNF-11). | F14: 1) Microservicios: descartada por complejidad operativa desproporcionada para tres aprendices, un trimestre y un parqueadero de referencia; obligaria a resolver comunicacion entre servicios y consistencia distribuida que el problema no pide. 2) Monolito en capas sin modularizar: descartada por acoplamiento; sin frontera de modulos las reglas de cobro y de cartera terminan repartidas entre pantallas, que es justamente el desorden que el proyecto viene a corregir. 3) Monolito con vistas renderizadas en el servidor y MVC (plantillas EJS o similares): mas simple de construir y el estilo que P04 describia; descartada porque el desarrollador frontend del equipo trabaja con React y porque es la habilidad de mayor valor profesional, y porque el unico riesgo tecnico que traia la SPA (la cookie de sesion entre dos dominios) se neutraliza con la redireccion de /api/*. 4) Backend repartido en funciones independientes sin nucleo monolitico: descartada porque dispersaria las reglas de negocio y haria imposible la verificacion de capas del apartado A.3 de P04. | G14: Permite verificar el apartado A.3 de P04 contra una decision real y no contra una referencia inexistente. Obliga a corregir en P04 la descripcion de CMP-01, que pasa de vista renderizada a aplicacion cliente, y a retirar la mencion al patron modelo-vista-controlador. La sesion viaja en cookie httpOnly y exige la redireccion de /api/* descrita en ADR-008 para que la cookie sea del mismo sitio. El codigo es monolitico pero el despliegue es serverless, distincion que conviene poder explicar en la sustentacion. Agrega HT-08 y mantiene vigente la disciplina de capas que permitio disenar el comportamiento antes de cerrar ADR-008.

Sheet Fuera de alcance
A1: Fuera de alcance (Won't have)
A2: Documentar lo que se decidió NO hacer, y por qué, vale tanto como documentar lo que si se hace. Evita que el alcance crezca en mitad del desarrollo, que es el riesgo de mayor probabilidad e impacto del Acta de Constitución.
A4: Elemento | B4: Categoría | C4: Por qué se deja fuera | D4: Que haría falta para incluirlo | E4: Origen
A5: Aviso automático de vencimiento de mensualidad | B5: Won't (v1) | C5: Exige un proceso programado que corra por fuera de la aplicación evaluando a diario los vencimientos de todas las afiliaciones. La información sigue disponible sin ese proceso: el cliente ve su fecha de vencimiento en RF-15 y el administrador ve el estado Por vencer en RF-14. | D5: Un planificador de tareas en el servidor. La lógica de estados (RN-12) ya quedaría hecha. | E5: Decisión del equipo, 14/08/2026
A6: Pago en línea del cliente | B6: Won't (v1) | C6: Requiere pasarela de pagos y conciliación. En la v1 el pago es presencial y lo registra el administrador. | D6: Integración con una pasarela y un proceso de conciliación. | E6: Acta de Constitución, Exclusiones
A7: Facturación electronica | B7: Won't (v1) | C7: Exige habilitación ante la DIAN y cumplimiento de un estándar técnico y tributario que excede el alcance academico. | D7: Habilitación como facturador electronico e integración con un proveedor tecnológico. | E7: Acta de Constitución, Exclusiones
A8: Lectura automática de placa por camara | B8: Won't (v1) | C8: Requiere hardware y visión por computador; excede el alcance y el presupuesto. El Acta la difiere expresamente a una segunda fase. | D8: Camaras, un modelo de reconocimiento y un proceso de validación manual de respaldo. | E8: Acta de Constitución, Exclusiones
A9: Aplicación móvil nativa | B9: Won't (v1) | C9: La plataforma es web responsiva. Una app nativa duplica el esfuerzo de desarrollo del equipo. | D9: Un desarrollo móvil aparte, o empaquetar la web existente. | E9: Acta de Constitución, Exclusiones
A10: Modulos de nómina, contabilidad o gestión del personal | B10: Won't (v1) | C10: Son sistemas distintos con su propia normatividad. El sistema administra la operación del parqueadero, no la empresa. | D10: Fuera del alcance academico. | E10: Acta de Constitución, Exclusiones
A11: Seguridad física y custodia de los vehículos | B11: Won't (siempre) | C11: No es una exclusión de versión sino una frontera permanente del producto: el sistema entrega trazabilidad administrativa de la operación, no custodia. Es el riesgo de expectativa más importante identificado en el documento de Stakeholders (STK-01, impacto alto) y debe declararse por escrito ante el cliente. | D11: No aplica. Debe quedar explicito en los términos y condiciones del sistema. | E11: Stakeholders, Riesgos STK-01
A12: Cobro de suscripción a los administradores | B12: Won't (v1) | C12: Convierte el proyecto en un producto comercial y agrega pasarela de pagos, facturación e impuestos. | D12: Fuera del alcance academico. | E12: Backlog v2
A13: Verificación de identidad del negocio al registrar un parqueadero | B13: Won't (v1) | C13: El parqueadero nace del registro del administrador (RF-01) sin comprobar que el negocio exista ni que quién lo registra sea su propietario. | D13: Un proceso de validación documental y un estado de parqueadero pendiente de aprobación. | E13: Backlog v2
A14: Panel de superadministrador y reportes entre parqueaderos | B14: Won't (v1) | C14: Contradice el aislamiento exigido por RNF-02 y no aporta valor al usuario objetivo. | D14: Un modelo de permisos por encima del inquilino y una revisión completa de RNF-02. | E14: Backlog v2
A15: Marca o dominio propio por parqueadero | B15: Won't (v1) | C15: Es personalización visual, no capacidad de negocio. | D15: Un modulo de personalización visual por parqueadero y, para el dominio, la gestión de certificados y de registros DNS. | E15: Backlog v2
A16: Reserva anticipada de celda | B16: Won't (v1) | C16: Es un producto distinto (marketplace) y no fue parte de la necesidad identificada en el Acta. | D16: Candidato para una versión futura. | E16: Backlog v2
A18: El rol de operario SALIO de esta hoja en la v3.0: entra a la primera versión. Ver ADR-005.
A20: La integración con hardware del parqueadero SALIO de esta hoja en la v3.2: el lector de código QR entra a la primera versión. Ver ADR-009. Continuan fuera de alcance las talanqueras, los sensores de celda y la lectura automática de placa por camara.

Sheet Control de cambios
A1: Control de cambios v2 -> v3.0
A2: Cambios aplicados el 14 de agosto de 2026 tras contrastar el backlog contra el Acta de Constitución (05/08/2026), el documento de Stakeholders v2 (12/08/2026) y el Análisis de Seguridad en la Implantación de Software.
A4: N | B4: Que cambio | C4: Como estaba en la v2 | D4: Como quedo en la v3 y por qué | E4: Impacto en el libro
A5: 1 | B5: Nombre del proyecto y ficha | C5: El libro se titulaba UrbanSpot y el encabezado citaba la ficha 228118 y las evidencias EV02 y EV03 de un proyecto formativo. | D5: APAR-CAR, ficha 3229209, proyecto de grado. Los documentos oficiales ya usaban el nombre APAR-CAR; el backlog había quedado con el nombre de trabajo anterior. | E5: Hojas Leeme, Resumen e Historias
A6: 2 | B6: Rol de operario | C6: Declarado Won't (v1) en la hoja Fuera de alcance, con el argumento de que multiplicaba los casos de permisos. | D6: Entra a la primera versión. El Acta lo promete en el objetivo general, en el objetivo específico 2 y en el Entregable 5, y Stakeholders lo clasifica como STK-02 usuario clave. Mantenerlo fuera era una contradicción entre entregables. Ver ADR-005. | E6: Actores, EP-01, EP-04, HU-03, HU-19 a HU-23, HU-38, HU-39, RNF-03, Fuera de alcance
A7: 3 | B7: Consulta de tiquete del cliente ocasional | C7: El visitante ocasional era un actor pasivo: entraba y salia sin ninguna forma de consultar nada. | D7: Puede consultar su tiquete abierto con un código entregado a la entrada, nunca con la placa, porque RN-06 establece que la placa identifica pero no autentica. Responde a la necesidad de STK-04. | E7: HU-20, HU-40, RN-15, NEC-09
A8: 4 | B8: Regla de cálculo del cobro (RN-14) | C8: Redondeo de la fracción a la hora superior y tarifa día a partir de un umbral fijo de 12 horas. Sin regla para estadías de varios días. | D8: Cobro proporcional por bloques de 24 horas, cobrando por bloque el menor entre el proporcional y la tarifa día, con mínimo de una hora. El umbral fijo cobraba por encima de la tarifa día entre el punto de equilibrio real y las 12 horas. Ver ADR-006. | E8: RN-14, HU-21, ADR-006
A9: 5 | B9: Derecho de supresión de datos (HU-37) | C9: Historia marcada como no estimable: el alcance legal de la anonimización estaba sin confirmar y chocaba con la inmutabilidad de los registros de dinero de RN-13. | D9: Dos estados: inhabilitación mientras exista deber contractual vigente, y anonimización cuando termine. Amparado en el Decreto 1377 de 2013, que excluye la supresión cuando el titular tiene un deber legal o contractual de permanecer en la base de datos. Ver ADR-007. | E9: HU-37, RN-08, RNF-05, ADR-007, INVEST
A10: 6 | B10: División de HU-12 | C10: Una sola historia de 8 puntos que mezclaba registrar al cliente con generar el código de vinculación. Marcada Revisar en el criterio Small de INVEST. | D10: Dividida en HU-12a (registrar cliente y vehículo, 5 puntos) y HU-12b (generar código, 3 puntos). Cada mitad se entrega y se prueba por separado. | E10: HU-12a, HU-12b, INVEST, dependencias de HU-13 a HU-17
A11: 7 | B11: HU-21 se mantiene unida | C11: Marcada Revisar en Small por sus 8 puntos, sin decisión registrada. | D11: Se mantiene unida por decisión del equipo, con la justificación escrita en INVEST: dividirla dejaría una primera mitad que libera la celda sin cobrar nada, lo cual no es un incremento entregable. | E11: INVEST
A12: 8 | B12: Aviso de vencimiento (antigua HU-31) | C12: Historia Could de 8 puntos, marcada Revisar en dos criterios INVEST por depender de un proceso programado. | D12: Retirada del alcance. La información sigue disponible en HU-25 y HU-29 sin necesidad de infraestructura adicional. | E12: Fuera de alcance, RN-12, HU-25, HU-29, NEC-04
A13: 9 | B13: Supuestos y decisiones abiertas | C13: Dos supuestos por confirmar (SUP-01 celdas, SUP-02 mensualidad) y dos ADR en estado Propuesta - CONFIRMAR. | D13: Eliminados. ADR-003 queda confirmada por el Acta de Constitución y ADR-004 por decisión del equipo. No queda ninguna decisión abierta en el backlog. | E13: Leeme, ADR-003, ADR-004, RN-11
A14: 10 | B14: Parametros sin aprobar | C14: El código de vinculación vencia a los 7 días y el estado Por vencer se activaba a los 5 días, ambos escritos como valor por defecto. | D14: Confirmados por el equipo: 7 días para el código y 3 días para el estado Por vencer. | E14: RN-05, RN-12
A15: 11 | B15: Requisito de código fuente (RNF-10) | C15: El riesgo R3 del Análisis de Seguridad (filtración del código fuente) no estaba cubierto por ningún requisito verificable. | D15: Se agrega RNF-10: repositorio privado, sin credenciales versionadas, configuración sensible por variables de entorno y revisión del historial antes de cada entrega. | E15: RNF-10, NEC-10
A16: 12 | B16: Trazabilidad con los demás entregables | C16: La matriz solo citaba la descripción del proyecto como origen y no se conectaba con el Acta ni con Stakeholders. | D16: Cada necesidad cita su apartado de origen en el Acta o en Stakeholders y su STK responsable; cada historia lleva su stakeholder; cada RNF lleva el riesgo del Análisis de Seguridad que mitiga. Se agregan NEC-08 a NEC-12, con lo cual toda historia del backlog queda trazada a una necesidad de negocio. | E16: Trazabilidad, Historias, RNF, Actores
A19: CORRECCIONES PENDIENTES EN LOS DEMÁS ENTREGABLES
A20: N | B20: Documento | C20: Que dice hoy | D20: Que debería decir | E20: Por qué importa
A21: 1 | B21: Acta de Constitución APAR-CAR | C21: Portada: Ficha 32292909 (ocho dígitos). | D21: Ficha 3229209 (siete dígitos). | E21: Dato de identificación del proyecto en la portada de un entregable evaluado.
A22: 2 | B22: Stakeholders APAR-CAR v2 | C22: Portada: Ficha 32292909 (ocho dígitos). | D22: Ficha 3229209 (siete dígitos). | E22: Mismo error replicado. Debe corregirse en los dos documentos a la vez.
A23: 3 | B23: Análisis de Seguridad | C23: Introducción: tiene roles distintos (administrador y cliente). | D23: Tiene tres roles distintos: administrador, operario y cliente. | E23: Contradice el Acta y el documento de Stakeholders. Es el riesgo STK-06, incoherencia entre entregables, calificado de impacto alto.
A24: 4 | B24: Análisis de Seguridad | C24: Riesgo R4 descrito solo como un cliente que escala privilegios de administrador. | D24: Incluir el escenario más probable con tres roles: un operario que accede a tarifas, cartera o reportes alterando la petición. | E24: Alinea el análisis de riesgos con el modelo de permisos real y con el criterio de verificación de RNF-03.
A25: 5 | B25: Acta de Constitución, Tabla 1 | C25: Entregable 2: Documento de requerimientos. | D25: Referenciar este libro como la versión vigente del entregable (backlog v3.0, 14/08/2026). | E25: Cierra la cadena de trazabilidad entre el Acta y el backlog.
A26: 13 | B26: Revisión de la priorización MoSCoW | C26: El 62,5 % de los puntos estaba clasificado como Must have. | D26: HU-23 (consultar vehículos adentro) y HU-32 (reporte de ingresos) pasan a Should have. El MVP queda en 92 de 160 puntos, es decir 57,5 %. La plantilla P02 del proyecto formativo establece que por encima del 60 % la priorización debe revisarse, y el análisis confirmo que ninguna de las dos historias bloquea la primera versión. | E26: Historias de Usuario, Resumen, P01, P02
A29: Control de cambios v3.1 -> v3.2
A30: Cambios aplicados el 28 de agosto de 2026 tras revisar la coherencia entre el backlog, la Formulación y Constitución, la Gestión de Interesados, el documento de Alcance y Especificación de Requisitos y los anexos de la plantilla P01.
A32: N | B32: Que cambio | C32: Como estaba en la v3.1 | D32: Como quedo en la v3.2 y por qué | E32: Impacto en el libro
A33: 1 | B33: Catálogo de requisitos funcionales | C33: El libro no tenía hoja de requisitos funcionales. Los RF-01 a RF-20 existían únicamente en el Anexo A de la plantilla P01, y el documento de Alcance los citaba como catálogo del proyecto sin que estuviera en la fuente de verdad. | D33: Se incorpora la hoja Requisitos Funcionales con los 20 requisitos del Anexo A, cada uno con su origen, su épica y las historias que lo implementan. La fuente de verdad vuelve a contener todos los catálogos. | E33: Hoja nueva Requisitos Funcionales, Resumen, Leeme
A34: 2 | B34: Registro de movimientos por código QR | C34: La Formulación anunciaba el registro de entrada y salida por medio del QR, pero el mismo documento excluía la integración con hardware y declaraba la digitación manual como limitación. El backlog recogia solo la exclusión: ninguna historia, regla ni ADR mencionaba el QR. | D34: Se resuelve la contradicción a favor del QR. Se adopta un lector físico propio sobre ESP32 que envía la lectura a la API, con confirmación del operario y registro manual como vía alterna permanente. Queda registrado en ADR-009. | E34: ADR-009, RF-21, RF-22, RN-15, RN-16, RN-17, RNF-11, HU-41 a HU-45, Fuera de alcance, Trazabilidad
A35: 3 | B35: Exclusión de integración con hardware | C35: La hoja Fuera de alcance declaraba Won't (v1) la integración con hardware del parqueadero, citando como origen las exclusiones del Acta de Constitución. | D35: Se retira la fila. Continuan fuera de alcance las talanqueras, los sensores de celda y la lectura automática de placa por camara. La ampliación queda justificada por escrito, como exige la mitigación del riesgo de alcance del Acta. | E35: Fuera de alcance, ADR-009
A36: 4 | B36: Vocabulario de roles, actores e interesados | C36: La hoja Resumen contaba 4 roles incluyendo Persona nueva y sin el cliente ocasional, mientras la Formulación y el documento de Alcance contaban 4 perfiles de usuario con el ocasional y sin Persona nueva. Ambos decían cuatro y no hablaban de lo mismo. | D36: Se separan tres categorías: 3 roles con credenciales, 5 actores del sistema y 6 interesados del proyecto. La hoja Actores gana una columna Tipo que lo hace explicito. Coincide con lo que ya decía ADR-005. | E36: Actores, Resumen, Leeme
A37: 5 | B37: Denominación del cliente afiliado | C37: La hoja Historias de Usuario usaba Cliente a secas en la columna Rol principal, termino que se confunde con el cliente ocasional. | D37: Se unifica en Cliente afiliado en todo el libro, igual que en la Formulación y en el documento de Alcance. | E37: Historias de Usuario, Actores
A38: 6 | B38: Versión y fecha del libro | C38: La portada y la hoja Leeme se identificaban como v3.0 y con fecha del 14 de agosto de 2026, aunque el archivo circulaba como v3.1. | D38: Se actualizan a v3.2 con fecha del 28 de agosto de 2026 en Leeme, Resumen e Historias de Usuario. | E38: Leeme, Resumen, Historias de Usuario
A39: 7 | B39: Etiqueta de ADR-005 en la hoja Leeme | C39: La hoja Leeme titulaba ADR-005 como Roles del sistema, mientras la hoja de decisiones lo define como Inclusión del rol operario en la primera versión. | D39: Se corrige el texto de Leeme para que cite la decisión tal como está registrada y para que enuncie los tres roles y los dos actores sin rol. | E39: Leeme
A40: 8 | B40: Atribución de NEC-06 en la matriz de trazabilidad | C40: La necesidad de aislamiento entre parqueaderos se atribuía a STK-01 y STK-05. El equipo de desarrollo no es titular de esa necesidad de negocio: la implementa. | D40: Queda atribuida únicamente a STK-01, el administrador del parqueadero. | E40: Trazabilidad
A41: 9 | B41: Ficha del proyecto en los entregables | C41: Las correcciones pendientes 1 y 2 de la v3.0 pedían corregir la ficha en el Acta de Constitución y en el documento de Stakeholders. | D41: Verificado el 28/08/2026: los tres documentos publicados (Formulación, Gestión de Interesados y Alcance y Requisitos) ya citan la ficha 3229209. Los dos pendientes se cierran. | E41: Correcciones pendientes
A43: PENDIENTES ABIERTOS AL CIERRE DE LA v3.2
A44: N | B44: Documento | C44: Que queda desalineado | D44: Que hay que hacer | E44: Por qué importa
A45: 1 | B45: P01 Historias de Usuario, Anexos A, B y C | C45: El Anexo A no incluye RF-21 ni RF-22. Los Anexos B y C reproducen la versión v3.0 de las reglas y de los requisitos no funcionales: RN-11 se contradice a si misma, RN-14 no resuelve la mora, RN-15 dice cada entrada, RN-05 no trae el bloqueo por intentos y RNF-01, RNF-06 y RNF-08 carecen de cifras verificables. No están RN-16, RN-17 ni RNF-11. | D45: Regenerar el documento P01 completo desde este libro: los tres anexos y las fichas de las historias HU-41 a HU-45. | E45: Aplazado por decisión del equipo el 28/08/2026. Los cuatro artefactos del proyecto se generan del mismo contenido y no pueden divergir; mientras no se regenere, el P01 es una copia atrasada y así queda declarado.
A46: 2 | B46: P02 Backlog estimado | C46: No incluye las historias HU-41 a HU-45 ni sus puntos en las hojas Backlog, Poker, Iteraciones y Resumen. | D46: Regenerar desde este libro y registrar la fecha real de la sesión de Planning Poker. | E46: Los totales de puntos y el porcentaje de Must cambian con las historias nuevas.
A47: 3 | B47: Formulación y Constitución del Proyecto | C47: Excluye la integración con hardware y declara como limitación que no se contempla lectura automática, en contradicción con su propia sección de Funciones Generales Incluidas. | D47: Retirar la exclusión de lectores, reescribir la limitación de digitación y agregar tabla de identificación y control de cambios. | E47: Es el documento de origen de la exclusión que ADR-009 retira.
A48: 4 | B48: Alcance y Especificación de Requisitos | C48: Excluye los lectores automáticos, declara MySQL y XAMPP como restricción, y enuncia RNF-01 y RNF-08 sin cifras verificables. RN-14 omite la clausula de mora que sus propios criterios de RF-12 aplican. | D48: Alinear alcance, exclusiones, restricciones, RNF y RN-14 con este libro. | E48: Un requisito no funcional sin cifra no es verificable, que es el criterio que el propio documento declara.
A49: 5 | B49: Análisis de Seguridad | C49: Dice roles distintos (administrador y cliente) y describe R4 solo como escalamiento de un cliente. | D49: Corregir a tres roles e incluir en R4 el escenario del operario que accede a tarifas, cartera o reportes. | E49: Pendiente heredado de la v3.0, sin resolver.
A50: 6 | B50: ADR-008 - stack tecnológico | C50: Sin decidir el lenguaje de servidor ni el framework. | D50: Decidir en la fase de Diseño y arquitectura. Confirmado el 28/08/2026 que el stack es un recurso disponible y no una restricción del proyecto. | E50: Condiciona los diagramas de secuencia y el contrato de la API.
A51: 7 | B51: Parqueadero de referencia | C51: Sin registrar cual se consiguió ni cuando se hizo la entrevista. | D51: Registrar el establecimiento y la fecha de la entrevista. | E51: Es el supuesto del que dependen las reglas de cobro y de cartera, y los tiempos del flujo actual que pide la plantilla P03.
A52: 8 | B52: Hardware del lector QR | C52: El equipo aún no dispone del ESP32 ni del modulo lector. | D52: Conseguir el hardware y probar la lectura contra la API antes de la sustentación. | E52: Riesgo acotado por HU-45: si el lector no está listo, el producto sigue siendo demostrable con registro manual.
A54: Control de cambios v3.2 -> v3.3
A55: Cambios aplicados el 9 de septiembre de 2026 al elaborar el documento de Backlog, Historias de Usuario y Casos de Uso (v2.0) y el documento de Casos de Uso y Escenarios (v1.1). El libro había quedado por detras de los documentos: esta versión lo vuelve a poner al frente.
A57: N | B57: Que cambio | C57: Como estaba en la v3.2 | D57: Como quedo en la v3.3 y por que | E57: Impacto en el libro
A58: 1 | B58: ADR-008 - stack tecnológico | C58: La numeración de las decisiones saltaba de ADR-007 a ADR-009. La hoja Resumen contaba 8 decisiones y la nota afirmaba que todas estaban Aceptadas, cifra que cuadraba por coincidencia. | D58: Se crea la decisión en estado Propuesta, con contexto, alternativas descartadas, criterios de cierre y consecuencias. Declararla abierta es preferible a resolverla sin análisis: una elección sin alternativas evaluadas no es un ADR sino una nota. | E58: Decisiones (ADR), Resumen, Leeme, Control de cambios
A59: 2 | B59: SUP-03 - presencia de operario | C59: El supuesto no existia en el libro. La épica EP-04, la de mayor esfuerzo con 42 puntos, descansaba sobre un acuerdo verbal con el administrador del parqueadero de referencia. | D59: Se crea la hoja Supuestos y se registra SUP-03 con lo que depende de el y lo que ocurre si no se cumple. El levantamiento del proceso real mostro que hoy el acceso no tiene cobertura permanente. | E59: Hoja nueva Supuestos, Resumen, Leeme
A60: 3 | B60: Notas de contexto en ADR-004 y ADR-006 | C60: Ambas decisiones se leian como si derivaran de la operación del parqueadero de referencia. | D60: Se agrega a las dos una nota que aclara que fueron definidas sobre el caso general del segmento: el parqueadero de referencia trabaja con fecha fija de pago dentro del mes y con valor discrecional para el visitante ocasional. La diferencia es deliberada y busca la replicabilidad. | E60: Decisiones (ADR)
A61: 4 | B61: Historias técnicas HT-01 a HT-04 | C61: El libro registraba decisiones de arquitectura pero no el trabajo que esas decisiones obligan a ejecutar. | D61: Se crea la hoja Historias Técnicas con cuatro elementos, cada uno amarrado al ADR que lo justifica. Ninguno nombra lenguaje ni framework, porque ADR-008 sigue en Propuesta. | E61: Hoja nueva Historias Técnicas, Resumen, Leeme
A62: 5 | B62: Casos de uso CU-01 a CU-06 | C62: El libro no tenía registro de casos de uso. Los tres primeros existían solo en el documento de la guía 4. | D62: Se crea la hoja Casos de Uso con seis casos y su justificación de selección. Los tres iniciales se concentraban en la operación de porteria y ninguno describia el proceso de cartera, que el propio análisis AS-IS había identificado como el problema central del negocio. | E62: Hoja nueva Casos de Uso, Resumen, Leeme
A63: 6 | B63: Tildes en todo el libro | C63: El texto de todas las hojas estaba escrito sin tildes ni enes: registrar la ocupación, el vehículo está adentro, cambio de dueño. | D63: Se restauran las tildes y las enes en las celdas de texto de las trece hojas originales. Los documentos publicados ya salian corregidos; el libro no. | E63: Todas las hojas
A64: 7 | B64: Versión y fecha del libro | C64: La portada y la hoja Leeme se identificaban como v3.2 con fecha del 28 de agosto de 2026. | D64: Se actualizan a v3.3 con fecha del 9 de septiembre de 2026. | E64: Leeme, Resumen
A65: 8 | B65: Ficha del proyecto | C65: La hoja Leeme citaba la ficha 32292909. | D65: Corregida a 3229209 en todo el libro. | E65: Leeme
A67: PENDIENTES ABIERTOS AL CIERRE DE LA v3.3
A68: N | B68: Documento o elemento | C68: Que queda desalineado | D68: Que hay que hacer | E68: Por que importa
A69: 1 | B69: Acta de Constitución y documento de Stakeholders | C69: Las portadas citan un número de ficha distinto de 3229209. | D69: Corregir la portada de los dos documentos. | E69: Es el dato que identifica al equipo ante la institución.
A70: 2 | B70: Análisis de Seguridad | C70: Habla de roles distintos (administrador y cliente) y describe R4 sin considerar al operario. | D70: Corregir a tres roles e incluir en R4 el escenario del operario que accede a tarifas, cartera o reportes. | E70: Pendiente heredado de la v3.0. Los RNF citan sus riesgos, de modo que la inconsistencia se propaga.
A71: 3 | B71: ADR-008 - stack tecnológico | C71: Registrada, pero en estado Propuesta. | D71: Cerrar la decisión en la fase de Diseño y arquitectura, con las alternativas evaluadas por escrito. | E71: Condiciona los diagramas de secuencia, el contrato de la API y las historias técnicas.
A72: 4 | B72: Estimación de HT-01 a HT-04 | C72: Las cuatro historias técnicas entran sin puntos. | D72: Estimarlas en la sesión de planificación junto con las historias de usuario. | E72: El total de puntos del proyecto queda incompleto mientras falten.
A73: 5 | B73: Casos de prueba | C73: La ultima columna de la hoja Trazabilidad sigue en Por definir. | D73: Completar en la fase de Pruebas y ajustes, del 1 al 22 de diciembre de 2026. Los 21 escenarios ya están redactados en un formato convertible a casos de prueba. | E73: Cierra la cadena Necesidad, Requisito, Historia, Caso de uso, Escenario, Prueba.
A74: 6 | B74: Caso de uso del derecho de supresión | C74: Cumple los criterios de selección pero no se específico. | D74: Decidir si se incorpora como CU-07. | E74: Es el único flujo del sistema con consecuencia legal directa. ADR-007 pidio validación del instructor.
A75: 7 | B75: Parqueadero de referencia | C75: Sigue sin registrarse el establecimiento y la fecha de la entrevista. | D75: Registrar el nombre y la fecha. El proceso actual ya quedo levantado y documentado en el AS-IS de la guía 4. | E75: Es la fuente del AS-IS y de las reglas de cobro y cartera.
A76: 8 | B76: Hardware del lector QR | C76: El equipo aún no dispone del microcontrolador ni del modulo lector. | D76: Conseguir el hardware y probar la lectura contra la API. | E76: Riesgo acotado por HU-45: si el lector no está listo, el proceso manual cubre la operación.
A78: Control de cambios v3.3 -> v3.4
A79: Cambios aplicados el 11 de septiembre de 2026 al cerrar la decision de stack tecnologico y al corregir las inconsistencias detectadas al construir la matriz de trazabilidad P05 y al revisar P03 y P04.
A81: N | B81: Que cambio | C81: Como estaba en la v3.3 | D81: Como quedo en la v3.4 y por que | E81: Impacto en el libro
A82: 1 | B82: ADR-008 - stack tecnologico | C82: Registrada en estado Propuesta, sin lenguaje de servidor ni motor de persistencia. | D82: Cerrada como Aceptada el 11/09/2026 con el stack completo, siete alternativas descartadas por escrito y el manejo de fechas en timestamptz UTC. Se decidio contra los tres criterios que la propia decision ya habia declarado. | E82: Decisiones (ADR), Historias Tecnicas, Leeme, Resumen
A83: 2 | B83: ADR-010 - estilo arquitectonico | C83: No existia. La plantilla P04 la citaba cuatro veces y verificaba los ocho diagramas contra ella. | D83: Se crea como Aceptada: monolito modular con cliente desacoplado. Se retira la mencion al patron modelo-vista-controlador, que dejo de aplicar al elegir React: el servidor ya no renderiza vistas. | E83: Decisiones (ADR), Leeme, Resumen; obliga a corregir el apartado A.1 de P04
A84: 3 | B84: HU-46 - bloqueo de cuenta por intentos fallidos | C84: RNF-01 exigia el bloqueo tras cinco intentos y DSQ-01 lo describia con su respuesta 423, pero ninguna de las 45 historias lo implementaba. | D84: Se crea HU-46 en EP-01, Must, 3 puntos, con los criterios de aceptacion del bloqueo, el tiempo restante y el asiento en bitacora. Un requisito no funcional sin historia que lo implemente no se construye. | E84: Historias de Usuario, INVEST, RF-02, RN-09, RNF-01, RNF-07, NEC-12, Resumen
A85: 4 | B85: HU-47 - anulacion de un pago con motivo | C85: RN-13 exigia la anulacion con motivo para los registros de dinero, y BPM-03 y DSQ-04 la describian como camino de excepcion, pero solo HU-22 la cubria y solo para movimientos. | D85: Se crea HU-47 en EP-05, Should, 5 puntos, con recalculo de vencimiento y de estado de cartera. P03 y P04 atribuian esta funcion a HU-26, cuyo titulo real es consultar el historial de pagos. | E85: Historias de Usuario, INVEST, RF-14, RN-11, RN-12, RN-13, RNF-07, NEC-03, Resumen
A86: 5 | B86: Historias tecnicas HT-05 a HT-08 | C86: El libro tenia cuatro historias tecnicas, todas anteriores a la decision de stack. | D86: Se agregan cuatro derivadas de ADR-008 y ADR-010: repositorio y despliegue continuo, esquema de Prisma sobre PostgreSQL, sesion en base de datos con bloqueo por intentos, y cliente React con consumo autenticado de la API. | E86: Historias Tecnicas, Leeme, Resumen
A87: 6 | B87: Enlaces cruzados de las historias nuevas | C87: Las columnas de historias de RF-02, RF-14, RN-09, RN-11, RN-12, RN-13, RNF-01, RNF-07, NEC-03 y NEC-12 no incluian HU-46 ni HU-47. | D87: Se agregan las dos historias en las diez filas correspondientes, para que la cadena de trazabilidad no quede rota en la matriz P05. | E87: Requisitos Funcionales, Reglas de Negocio, Requisitos No Funcionales, Trazabilidad
A88: 7 | B88: Implementacion de los requisitos no funcionales | C88: Los RNF no podian nombrar tecnologia porque ADR-008 estaba abierta. | D88: Los criterios de verificacion NO cambian. La implementacion queda registrada en las consecuencias de ADR-008: RNF-01 con express-session y bcrypt mas HU-46, RNF-02 con extensiones de cliente de Prisma, RNF-11 contra un endpoint sin estado. | E88: Decisiones (ADR); los RNF conservan su redaccion
A89: 8 | B89: Version y fecha del libro | C89: La portada y la hoja Leeme se identificaban como v3.3 con fecha del 9 de septiembre de 2026. | D89: Se actualizan a v3.4 con fecha del 11 de septiembre de 2026, y se corrige el conteo de decisiones de arquitectura, que decia 9 con una en Propuesta. | E89: Leeme, Resumen
A91: PENDIENTES ABIERTOS AL CIERRE DE LA v3.4
A92: N | B92: Documento o elemento | C92: Que queda desalineado | D92: Que hay que hacer | E92: Por que importa
A93: 1 | B93: Acta de Constitucion y documento de Stakeholders | C93: Las portadas citan un numero de ficha distinto de 3229209. | D93: Corregir la portada de los dos documentos. | E93: Es el dato que identifica al equipo ante la institucion.
A94: 2 | B94: Analisis de Seguridad | C94: Habla de roles distintos (administrador y cliente) y describe R4 sin considerar al operario. | D94: Corregir a tres roles e incluir en R4 el escenario del operario que accede a tarifas, cartera o reportes. | E94: Pendiente heredado de la v3.0. Los RNF citan sus riesgos, de modo que la inconsistencia se propaga.
A95: 3 | B95: P04 Modelo UML, apartado A.1 | C95: Describe CMP-01 como presentacion con patron modelo-vista-controlador, que ADR-010 acaba de retirar. | D95: Reescribir la fila de CMP-01 como aplicacion cliente independiente y la nota de estilo arquitectonico. | E95: Es el documento que cita ADR-010; si no se corrige, la verificacion del apartado A.3 sigue siendo falsa.
A96: 4 | B96: Formulacion, Alcance y Especificacion de Requisitos | C96: Declaran MySQL y XAMPP como recursos y no mencionan PostgreSQL, Vercel ni el resto del stack. | D96: Actualizar la tabla de recursos y las restricciones tecnologicas conforme a ADR-008. | E96: ADR-008 justifica la desviacion, pero los documentos de origen siguen diciendo otra cosa.
A97: 5 | B97: Estimacion de HT-01 a HT-08 | C97: Las ocho historias tecnicas entran sin puntos. | D97: Estimarlas en la sesion de planificacion junto con las historias de usuario. | E97: El total de puntos del proyecto queda incompleto mientras falten.
A98: 6 | B98: Hoja INVEST | C98: Solo llega hasta HU-40: HU-41 a HU-45 nunca se evaluaron, y HU-46 y HU-47 se agregaron en esta version. | D98: Completar la evaluacion INVEST de HU-41 a HU-45. | E98: Pendiente heredado de la v3.0, detectado al actualizar la hoja en la v3.4.
A99: 7 | B99: Casos de prueba | C99: La ultima columna de la hoja Trazabilidad sigue en Por definir, y la matriz P05 no tiene ninguna fila con cobertura completa. | D99: Completar en la fase de Pruebas y ajustes, del 1 al 22 de diciembre de 2026, con Vitest y Supertest segun ADR-008. | E99: Cierra la cadena Necesidad, Requisito, Historia, Caso de uso, Escenario, Prueba, y es lo unico que falta para que la P05 pase de cobertura Parcial a Completa.
A100: 8 | B100: Caso de uso del derecho de supresion | C100: Cumple los criterios de seleccion pero no se especifico. | D100: Decidir si se incorpora como CU-07. | E100: Es el unico flujo del sistema con consecuencia legal directa. ADR-007 pidio validacion del instructor.
A101: 9 | B101: Parqueadero de referencia | C101: Sigue sin registrarse el establecimiento y la fecha de la entrevista. | D101: Registrar el nombre y la fecha. | E101: Es la fuente del AS-IS y de las reglas de cobro y cartera.
A102: 10 | B102: Hardware del lector QR | C102: El equipo aun no dispone del microcontrolador ni del modulo lector. | D102: Conseguir el hardware y probar la lectura contra la API. | E102: Riesgo acotado por HU-45: si el lector no esta listo, el proceso manual cubre la operacion.
A103: 11 | B103: Validacion del stack con el instructor | C103: ADR-008 se cierra sobre planes gratuitos de terceros y se aparta de los recursos del Acta. | D103: Presentar la decision al instructor antes de iniciar la construccion. | E103: Es el mismo tipo de validacion que ADR-007 pidio para el derecho de supresion.
A105: Control de cambios v3.4 -> v3.5
A106: Cambios aplicados el 11 de septiembre de 2026 al alinear la plantilla P04 con el backlog.
A108: N | B108: Que cambio | C108: Como estaba en la v3.4 | D108: Como quedo en la v3.5 y por que | E108: Impacto en el libro
A109: 1 | B109: HU-43 - criterio del acuse al dispositivo lector | C109: La historia describía la lectura del código pero no acotaba qué información puede devolver el sistema al dispositivo. La restricción se decidió al modelar DSQ-02 en la plantilla P04 y quedó anotada allí como pendiente de trasladar al backlog. | D109: Se agrega un cuarto criterio de aceptación: la respuesta al lector es solo un acuse de recibo, sin placa, afiliación ni ningún dato del vehículo, para que un lector comprometido no exponga información. Se suma RNF-05 a su trazabilidad. | E109: Historias de Usuario, Requisitos No Funcionales
A110: 2 | B110: Catálogo de endpoints API-01 a API-12 | C110: La plantilla P04 los declaraba pendientes de consolidación hasta cerrar ADR-008. | D110: Con ADR-008 cerrada, las rutas quedan declaradas definitivas en P04. El libro no cambia, pero se deja constancia porque cierra un pendiente de aquella plantilla. | E110: Ninguno en el libro; se registra por trazabilidad
A111: 3 | B111: Versión y fecha del libro | C111: Se identificaba como v3.4 con fecha del 11 de septiembre de 2026. | D111: Se actualiza a v3.5, misma fecha, porque los dos cambios se aplicaron en la misma jornada de trabajo sobre P04. | E111: Leeme, Resumen
A113: PENDIENTES ABIERTOS AL CIERRE DE LA v3.5
A114: N | B114: Documento o elemento | C114: Que queda desalineado | D114: Que hay que hacer | E114: Por que importa
A115: 1 | B115: Acta de Constitución y documento de Stakeholders | C115: Las portadas citan un número de ficha distinto de 3229209. | D115: Corregir la portada de los dos documentos. | E115: Es el dato que identifica al equipo ante la institución.
A116: 2 | B116: Análisis de Seguridad | C116: Habla de roles distintos (administrador y cliente) y describe R4 sin considerar al operario. | D116: Corregir a tres roles e incluir en R4 el escenario del operario que accede a tarifas, cartera o reportes. | E116: Pendiente heredado de la v3.0. Los RNF citan sus riesgos, de modo que la inconsistencia se propaga.
...

Sheet Historias Tecnicas
A1: Historias técnicas y trabajo de soporte
A2: Una decisión de arquitectura registrada no es una historia técnica. El ADR documenta por qué se eligio un camino; la historia técnica es el trabajo que esa decisión obliga a ejecutar. La decisión justifica la tarea, no la sustituye. Ninguna de estas historias nombra lenguaje, framework ni biblioteca, porque ADR-008 sigue en estado Propuesta.
A4: ID | B4: Historia tecnica | C4: Tipo | D4: Alcance | E4: ADR que la justifica | F4: Reglas y RNF | G4: Por que es necesaria | H4: Que habilita | I4: Puntos | J4: Estado
A5: HT-01 | B5: Preparar la estructura de persistencia multi-inquilino | C5: Estructura de datos | D5: Todas las tablas operativas llevan el discriminador de parqueadero y las restricciones de unicidad se definen por parqueadero, no de forma global. | E5: ADR-001 | F5: RNF-02, RN-04 | G5: Sin esta estructura ninguna consulta puede aislarse por parqueadero y RNF-02, calificado como critico, no se puede verificar. La unicidad de la placa depende de ella. | H5: EP-02 a EP-08 | I5: Por estimar | J5: Por hacer
A6: HT-02 | B6: Construir la bitácora de auditoría solo anexable | C6: Seguridad | D6: Registro de usuario, fecha, hora y motivo, sin operación de modificación ni de eliminación disponible para ningún rol. | E6: ADR-007 | F6: RN-13, RNF-07 | G6: RN-13 declara inmutables los registros de dinero y RNF-07 exige que ninguna operación sensible quede sin rastro. La anonimización prevista en ADR-007 solo es defendible ante un requerimiento legal si existe evidencia de que se hizo y cuando. | H6: EP-08, HU-22, HU-26, HU-36, HU-37 | I6: Por estimar | J6: Por hacer
A7: HT-03 | B7: Construir el dispositivo lector de código QR | C7: Integración | D7: Microcontrolador con modulo de lectura y punto de integración que recibe el código leido y el identificador del punto de lectura. | E7: ADR-009 | F7: RN-16, RNF-11 | G7: Es hardware propio del equipo y no corresponde a ninguna historia de usuario, pero HU-43, HU-44 y HU-45 dependen de el. RNF-11 exige que el lector se autentique con clave propia revocable. | H7: HU-43, HU-44, HU-45 | I7: Por estimar | J7: Por hacer
A8: HT-04 | B8: Implementar el cálculo de los estados de cartera | C8: Estructura de datos | D8: Los cuatro estados de RN-12 se derivan de la fecha de vencimiento y se evaluan en el momento de la consulta. | E8: ADR-004 | F8: RN-11, RN-12 | G8: El estado Por vencer, que se activa tres días antes del vencimiento, no se produce solo: alguien debe calcularlo. Se resuelve por cálculo en consulta y no por proceso programado, coherente con la exclusión del aviso automático de vencimiento. | H8: HU-24, HU-25, HU-27, HU-29 | I8: Por estimar | J8: Por hacer
A9: HT-05 | B9: Preparar el repositorio, el despliegue y la integracion continua | C9: Infraestructura | D9: Un repositorio con las carpetas api/ y web/, dos proyectos en Vercel apuntando a el, la redireccion de /api/* hacia el servidor, las variables de entorno por ambiente y un flujo de GitHub Actions que corra ESLint, Prettier y Vitest en cada push, con SonarCloud conectado. | E9: ADR-008 | F9: RNF-04, RNF-10 | G9: Sin la redireccion de /api/* la cookie de sesion queda entre dominios distintos y la autenticacion no funciona. Sin el flujo de integracion continua, las metricas de la P06 no tienen de donde salir. | H9: Todas las epicas; habilita las metricas MET-01 a MET-12 de la P06 | I9: Por estimar | J9: Por hacer
A10: HT-06 | B10: Definir el esquema de Prisma y las migraciones sobre PostgreSQL | C10: Estructura de datos | D10: Modelo de datos completo en el esquema de Prisma con el discriminador parqueadero_id de ADR-001, migraciones versionadas, y todas las marcas de tiempo como timestamptz en UTC. Incluye la extension de cliente que centraliza el filtro por parqueadero. | E10: ADR-008, ADR-001 | F10: RNF-02, RN-04 | G10: Es la traduccion de HT-01 a la tecnologia elegida. La extension de cliente evita que RNF-02 dependa de recordar el filtro en cada consulta, que es el punto donde un olvido expone datos de otro parqueadero. | H10: EP-02 a EP-08 | I10: Por estimar | J10: Por hacer
A11: HT-07 | B11: Implementar la sesion en PostgreSQL con bcrypt y el bloqueo por intentos | C11: Seguridad | D11: Sesion con express-session almacenada en PostgreSQL con expiracion a treinta minutos, hash de contrasena con bcrypt, contador de intentos fallidos por cuenta y bloqueo de quince minutos con informe del tiempo restante. | E11: ADR-008 | F11: RNF-01, RN-09, RNF-07 | G11: En un despliegue serverless la sesion no puede vivir en memoria del proceso. El bloqueo de cuenta que exige RNF-01 no lo resuelve ninguna biblioteca del stack: es logica propia. | H11: HU-03, HU-04, HU-46 y toda operacion autenticada | I11: Por estimar | J11: Por hacer
A12: HT-08 | B12: Levantar el cliente React con Vite y Bootstrap y el consumo autenticado de la API | C12: Presentacion | D12: Proyecto de React con Vite, Bootstrap 5 con react-bootstrap, enrutamiento por rol, cliente HTTP que envia las credenciales de sesion, y manejo unificado de los errores 401, 403 y 423 que devuelve el servidor. | E12: ADR-010, ADR-008 | F12: RNF-03, RNF-08, RNF-06 | G12: ADR-010 convierte la presentacion en una aplicacion separada: el enrutamiento por rol y el manejo de sesion expirada dejan de ser responsabilidad del servidor y hay que construirlos en el cliente. | H12: Los tres paneles de EP-01 a EP-08; habilita el hito HI-08 | I12: Por estimar | J12: Por hacer

Sheet Casos de Uso
A1: Casos de uso especificados en detalle
A2: No se construyo un caso de uso por cada historia. Se seleccionaron los seis flujos que cumplen la mayoria de las ocho condiciones de selección: varias decisiones, distintos actores, alternativas importantes, errores relevantes, reglas complejas, información sensible y criticidad para el producto. La especificación completa, con los flujos desarrollados paso a paso y los 21 escenarios, vive en el documento Casos de Uso y Escenarios v1.1. Las épicas EP-06, EP-07 y EP-08 no tienen caso propio: son consultas de solo lectura sin bifurcaciones.
A4: ID | B4: Nombre | C4: Actor principal | D4: Actores secundarios | E4: RF | F4: Historias | G4: Reglas | H4: ADR | I4: Alternativos | J4: Escenarios | K4: Por que amerita el detalle
A5: CU-01 | B5: Registrar la salida de un vehículo y liquidar el cobro | C5: Operario | D5: Cliente afiliado, cliente ocasional, lector QR | E5: RF-12, RF-13 | F5: HU-21, HU-22, HU-44 | G5: RN-03, RN-10, RN-13, RN-14, RN-15, RN-16 | H5: ADR-006 | I5: 5 flujos | J5: 4 escenarios | K5: Único punto donde se determina un valor en dinero. Se bifurca según el estado de cartera y aplica el cálculo por bloques de 24 horas sobre la tarifa congelada en la entrada.
A6: CU-02 | B6: Registrar la entrada de un vehículo y asignar celda | C6: Operario | D6: Cliente afiliado, cliente ocasional, lector QR | E6: RF-11, RF-22 | F6: HU-19, HU-20, HU-43 | G6: RN-01, RN-03, RN-04, RN-10, RN-15, RN-16, RN-17 | H6: ADR-003, ADR-009 | I6: 5 flujos | J6: 4 escenarios | K6: Concentra la mayor cantidad de validaciones previas: formato de placa, presencia única, celda compatible y congelamiento de tarifa. Es la operación más frecuente del día.
A7: CU-03 | B7: Vincular la cuenta del cliente con su vehículo y su parqueadero | C7: Cliente afiliado | D7: Administrador, que emite el código | E7: RF-10 | F7: HU-12b, HU-13 | G7: RN-04, RN-05, RN-06, RN-07, RN-08 | H7: ADR-002 | I7: 4 flujos | J7: 4 escenarios | K7: Es donde el sistema decide si una persona puede ver la información de un vehículo. Un error de diseño permitiria consultar movimientos ajenos conociendo solo la placa.
A8: CU-04 | B8: Registrar el pago de una mensualidad y actualizar el período | C8: Administrador | D8: Cliente afiliado, que verifica el resultado | E8: RF-14 | F8: HU-24, HU-25, HU-26 | G8: RN-11, RN-12, RN-13 | H8: ADR-004 | I8: 4 flujos | J8: 3 escenarios | K8: Es el proceso que el análisis AS-IS identifico como el problema central del negocio. RN-11 encadena el período desde el vencimiento anterior si el pago es oportuno y desde la fecha de pago si es tardio.
A9: CU-05 | B9: Configurar el parqueadero: celdas y tarifas | C9: Administrador | D9: Ninguno | E9: RF-05, RF-07, RF-08 | F9: HU-07, HU-09, HU-10, HU-11 | G9: RN-01, RN-02, RN-03 | H9: ADR-001, ADR-003 | I9: 4 flujos | J9: 3 escenarios | K9: Hace visible la decisión estructural del proyecto: la unicidad del código de celda se verifica por parqueadero y no de forma global. Concentra el versionado de tarifas y su congelamiento.
A10: CU-06 | B10: Afiliar un cliente con su vehículo y emitir el código de vinculación | C10: Administrador | D10: Cliente afiliado, que recibe el código | E10: RF-09, RF-10 | F10: HU-12a, HU-14, HU-17 | G10: RN-04, RN-05, RN-06, RN-08, RN-09 | H10: ADR-002 | I10: 4 flujos | J10: 3 escenarios | K10: Contraparte de CU-03 desde el administrador. Sin este caso el código que CU-03 consume no tendria origen. Es donde se capturan datos personales de un tercero, lo que activa RN-08.

Sheet Supuestos
A1: Supuestos del proyecto
A2: Un supuesto es una condición que se da por cierta sin haberla verificado y de la que depende una parte del alcance. Los supuestos SUP-01 y SUP-02 de versiones anteriores se cerraron al confirmarse ADR-003 y ADR-004. SUP-03 nace del levantamiento del proceso real realizado para el documento de la guía 4.
A4: ID | B4: Supuesto | C4: Estado | D4: Registrado | E4: Enunciado | F4: De que depende | G4: Origen | H4: Que pasa si no se cumple
A5: SUP-03 | B5: Presencia de operario en el acceso | C5: Abierto | D5: 09/09/2026 | E5: El modelo objetivo supone que el parqueadero cuenta con una persona en el rol de operario que atiende el acceso. | F5: EP-04 (42 puntos), ADR-009, CU-01, CU-02, HT-03 | G5: El levantamiento del proceso real mostro que en el parqueadero de referencia el acceso no tiene cobertura permanente y que los clientes permanentes entran y salen con llave propia sin registro alguno. El administrador manifesto su acuerdo con el modelo propuesto, pero hasta la v3.2 ese acuerdo solo existia de forma verbal. | H5: Si el supuesto no se sostiene, la épica de mayor esfuerzo del backlog queda sin quien la ejecute y el lector QR de ADR-009 pierde su punto de operación.
